[
{"id": 1, "country": "Algeria", "operator": "Mobilis", "company_wiki_url": "https://en.wikipedia.org/wiki/Mobilis_(Algeria)"},
{"id": 2, "country": "Algeria", "operator": "Djezzy", "company_wiki_url": "https://en.wikipedia.org/wiki/Djezzy"},
{"id": 3, "country": "Algeria", "operator": "Ooredoo", "company_wiki_url": "https://en.wikipedia.org/wiki/Ooredoo_Algeria"},
{"id": 4, "country": "Angola", "operator": "Unitel", "company_wiki_url": "https://en.wikipedia.org/wiki/Unitel_(Angola)"},
{"id": 5, "country": "Angola", "operator": "Movicel", "company_wiki_url": "https://en.wikipedia.org/wiki/Movicel"},
{"id": 6, "country": "Angola", "operator": "Africell", "company_wiki_url": "https://en.wikipedia.org/wiki/Africell"},
{"id": 7, "country": "Bahrain", "operator": "Batelco", "company_wiki_url": "https://en.wikipedia.org/wiki/Batelco"},
{"id": 8, "country": "Bahrain", "operator": "Zain", "company_wiki_url": "https://en.wikipedia.org/wiki/Zain_Group"},
{"id": 9, "country": "Bahrain", "operator": "stc", "company_wiki_url": "https://en.wikipedia.org/wiki/Stc_Bahrain"},
{"id": 10, "country": "Benin", "operator": "MTN", "company_wiki_url": "https://en.wikipedia.org/wiki/MTN_Group"},
{"id": 11, "country": "Benin", "operator": "Glo", "company_wiki_url": "https://en.wikipedia.org/wiki/Globacom"},
{"id": 12, "country": "Benin", "operator": "BBcom", "company_wiki_url": null},
{"id": 13, "country": "Burkina Faso", "operator": "Mascom", "company_wiki_url": "https://en.wikipedia.org/wiki/Mascom"},
{"id": 14, "country": "Burkina Faso", "operator": "Orange", "company_wiki_url": "https://en.wikipedia.org/wiki/Orange_S.A."},
{"id": 15, "country": "Burkina Faso", "operator": "btc", "company_wiki_url": "https://en.wikipedia.org/wiki/Botswana_Telecommunications_Corporation"},
{"id": 16, "country": "Burundi", "operator": "Orange", "company_wiki_url": "https://en.wikipedia.org/wiki/Orange_S.A."},
{"id": 17, "country": "Burundi", "operator": "Onatel", "company_wiki_url": null},
{"id": 18, "country": "Burundi", "operator": "Telecel Faso", "company_wiki_url": null},
{"id": 19, "country": "Cabo Verde", "operator": "Lumitel", "company_wiki_url": "https://en.wikipedia.org/wiki/Lumitel"},
{"id": 20, "country": "Cabo Verde", "operator": "ONAMOB", "company_wiki_url": null},
{"id": 21, "country": "Cameroon", "operator": "CV Móvel", "company_wiki_url": null},
{"id": 22, "country": "Cameroon", "operator": "T-MAIS", "company_wiki_url": null},
{"id": 23, "country": "Central African Republic", "operator": "MTN", "company_wiki_url": "https://en.wikipedia.org/wiki/MTN_Group"},
{"id": 24, "country": "Central African Republic", "operator": "Orange", "company_wiki_url": "https://en.wikipedia.org/wiki/Orange_S.A."},
{"id": 25, "country": "Central African Republic", "operator": "Nexttel", "company_wiki_url": "https://en.wikipedia.org/wiki/Viettel_Mobile"},
{"id": 26, "country": "Central African Republic", "operator": "Camtel", "company_wiki_url": "https://en.wikipedia.org/wiki/Camtel"},
{"id": 27, "country": "Central African Republic", "operator": "YooMee", "company_wiki_url": null},
{"id": 28, "country": "Chad", "operator": "telecel", "company_wiki_url": "https://en.wikipedia.orghttps://fr.wikipedia.org/wiki/Telecel_Centrafrique"},
{"id": 29, "country": "Chad", "operator": "Orange", "company_wiki_url": "https://en.wikipedia.org/wiki/Orange_S.A."},
{"id": 30, "country": "Chad", "operator": "azur", "company_wiki_url": "https://en.wikipedia.org/wiki/NationLink_Telecom"},
{"id": 31, "country": "Chad", "operator": "Moov Africa", "company_wiki_url": "https://en.wikipedia.orghttps://fr.wikipedia.org/wiki/Moov_Centrafrique"},
{"id": 32, "country": "Comoros", "operator": "Moov", "company_wiki_url": "https://en.wikipedia.org/wiki/Moov"},
{"id": 33, "country": "Comoros", "operator": "Airtel", "company_wiki_url": "https://en.wikipedia.org/wiki/Airtel_Africa"},
{"id": 34, "country": "Congo", "operator": "HURI", "company_wiki_url": null},
{"id": 35, "country": "Côte d'Ivoire", "operator": "MTN", "company_wiki_url": "https://en.wikipedia.org/wiki/Mobile_Telephone_Networks"},
{"id": 36, "country": "Côte d'Ivoire", "operator": "Airtel", "company_wiki_url": "https://en.wikipedia.org/wiki/Airtel_Africa"},
{"id": 37, "country": "Côte d'Ivoire", "operator": "Azur", "company_wiki_url": null},
{"id": 38, "country": "Democratic Republic of the Congo", "operator": "Orange", "company_wiki_url": "https://en.wikipedia.org/wiki/Orange_S.A."},
{"id": 39, "country": "Democratic Republic of the Congo", "operator": "MTN", "company_wiki_url": "https://en.wikipedia.org/wiki/MTN_Group"},
{"id": 40, "country": "Democratic Republic of the Congo", "operator": "GreenN", "company_wiki_url": null},
{"id": 41, "country": "Democratic Republic of the Congo", "operator": "Warid", "company_wiki_url": "https://en.wikipedia.org/wiki/Warid_Telecom"},
{"id": 42, "country": "Democratic Republic of the Congo", "operator": "Mobile Cafe", "company_wiki_url": null},
{"id": 43, "country": "Democratic Republic of the Congo", "operator": "YooMee", "company_wiki_url": null},
{"id": 44, "country": "Djibouti", "operator": "Vodacom", "company_wiki_url": "https://en.wikipedia.org/wiki/Vodacom"},
{"id": 45, "country": "Djibouti", "operator": "Orange", "company_wiki_url": "https://en.wikipedia.org/wiki/Orange_RDC"},
{"id": 46, "country": "Djibouti", "operator": "Africell", "company_wiki_url": "https://en.wikipedia.org/wiki/Africell"},
{"id": 47, "country": "Djibouti", "operator": "Airtel", "company_wiki_url": "https://en.wikipedia.org/wiki/Airtel_Africa"},
{"id": 48, "country": "Egypt", "operator": "Evatis", "company_wiki_url": null},
{"id": 49, "country": "Equatorial Guinea", "operator": "Vodafone", "company_wiki_url": "https://en.wikipedia.org/wiki/Vodafone_Egypt"},
{"id": 50, "country": "Equatorial Guinea", "operator": "Orange", "company_wiki_url": "https://en.wikipedia.org/wiki/Orange_Egypt"},
{"id": 51, "country": "Equatorial Guinea", "operator": "Etisalat", "company_wiki_url": "https://en.wikipedia.org/wiki/Etisalat_Egypt"},
{"id": 52, "country": "Equatorial Guinea", "operator": "Telecom Egypt", "company_wiki_url": "https://en.wikipedia.org/wiki/Telecom_Egypt"},
{"id": 53, "country": "Eritrea", "operator": "Orange", "company_wiki_url": "https://en.wikipedia.org/wiki/Orange_S.A."},
{"id": 54, "country": "Ethiopia", "operator": "Eritel", "company_wiki_url": "https://en.wikipedia.org/wiki/Eritel"},
{"id": 55, "country": "Gabon", "operator": "Ethiotelecom", "company_wiki_url": "https://en.wikipedia.org/wiki/Ethiopian_Telecommunications_Corporation"},
{"id": 56, "country": "Gabon", "operator": "Safaricom Ethiopia", "company_wiki_url": null},
{"id": 57, "country": "Gambia", "operator": "Airtel", "company_wiki_url": "https://en.wikipedia.org/wiki/Airtel_Africa"},
{"id": 58, "country": "Gambia", "operator": "Moov Africa Gabon Telecom", "company_wiki_url": "https://en.wikipedia.org/wiki/Gabon_Telecom"},
{"id": 59, "country": "Ghana", "operator": "Africell", "company_wiki_url": "https://en.wikipedia.org/wiki/Africell"},
{"id": 60, "country": "Ghana", "operator": "Comium", "company_wiki_url": null},
{"id": 61, "country": "Ghana", "operator": "Gamcel", "company_wiki_url": "https://en.wikipedia.org/wiki/Gamtel"},
{"id": 62, "country": "Ghana", "operator": "Qcell", "company_wiki_url": null},
{"id": 63, "country": "Guinea", "operator": "MTN", "company_wiki_url": "https://en.wikipedia.org/wiki/MTN_Ghana"},
{"id": 64, "country": "Guinea", "operator": "Vodafone", "company_wiki_url": "https://en.wikipedia.org/wiki/Vodafone_Ghana"},
{"id": 65, "country": "Guinea", "operator": "Glo", "company_wiki_url": "https://en.wikipedia.org/wiki/Globacom"},
{"id": 66, "country": "Guinea-Bissau", "operator": "Orange", "company_wiki_url": "https://en.wikipedia.org/wiki/Orange_S.A."},
{"id": 67, "country": "Guinea-Bissau", "operator": "MTN", "company_wiki_url": "https://en.wikipedia.org/wiki/MTN_Group"},
{"id": 68, "country": "Guinea-Bissau", "operator": "Cellcom Guinée", "company_wiki_url": null},
{"id": 69, "country": "Guinea-Bissau", "operator": "Intercel", "company_wiki_url": null},
{"id": 70, "country": "Guinea-Bissau", "operator": "Sotelgui", "company_wiki_url": null},
{"id": 71, "country": "Iran", "operator": "MTN", "company_wiki_url": "https://en.wikipedia.org/wiki/MTN_Group#Coverage"},
{"id": 72, "country": "Iran", "operator": "Orange", "company_wiki_url": "https://en.wikipedia.org/wiki/Orange_S.A."},
{"id": 73, "country": "Iran", "operator": "Guinetel", "company_wiki_url": "https://en.wikipedia.orghttps://pt.wikipedia.org/wiki/Guinetel"},
{"id": 74, "country": "Iraq", "operator": "Hamrahe Aval", "company_wiki_url": "https://en.wikipedia.org/wiki/Mobile_Telecommunication_Company_of_Iran"},
{"id": 75, "country": "Iraq", "operator": "Irancell", "company_wiki_url": "https://en.wikipedia.org/wiki/MTN_Irancell"},
{"id": 76, "country": "Iraq", "operator": "RighTel", "company_wiki_url": "https://en.wikipedia.org/wiki/RighTel_Communications"},
{"id": 77, "country": "Israel", "operator": "Zain", "company_wiki_url": "https://en.wikipedia.org/wiki/Zain_Group"},
{"id": 78, "country": "Israel", "operator": "Asia Cell", "company_wiki_url": "https://en.wikipedia.org/wiki/Asia_Cell"},
{"id": 79, "country": "Israel", "operator": "Korek", "company_wiki_url": "https://en.wikipedia.org/wiki/Korek_Telecom"},
{"id": 80, "country": "Israel", "operator": "Omnnea", "company_wiki_url": null},
{"id": 81, "country": "Israel", "operator": "Itisaluna", "company_wiki_url": null},
{"id": 82, "country": "Jordan", "operator": "Cellcom", "company_wiki_url": "https://en.wikipedia.org/wiki/Cellcom_(Israel)"},
{"id": 83, "country": "Jordan", "operator": "Partner", "company_wiki_url": "https://en.wikipedia.org/wiki/Partner_Communications_Company"},
{"id": 84, "country": "Jordan", "operator": "Pelephone", "company_wiki_url": "https://en.wikipedia.org/wiki/Pelephone"},
{"id": 85, "country": "Jordan", "operator": "Hot Mobile", "company_wiki_url": "https://en.wikipedia.org/wiki/Hot_Mobile"},
{"id": 86, "country": "Jordan", "operator": "Golan Telecom", "company_wiki_url": "https://en.wikipedia.org/wiki/Golan_Telecom"},
{"id": 87, "country": "Jordan", "operator": "XFONE", "company_wiki_url": "https://en.wikipedia.org/wiki/XFONE"},
{"id": 88, "country": "Jordan", "operator": "Rami Levy", "company_wiki_url": "https://en.wikipedia.org/wiki/Rami_Levy_Communications"},
{"id": 89, "country": "Kenya", "operator": "Zain Jordan", "company_wiki_url": "https://en.wikipedia.org/wiki/Zain_Group"},
{"id": 90, "country": "Kenya", "operator": "Orange Jordan", "company_wiki_url": "https://en.wikipedia.org/wiki/Orange_Jordan"},
{"id": 91, "country": "Kenya", "operator": "Umniah", "company_wiki_url": "https://en.wikipedia.org/wiki/Umniah"},
{"id": 92, "country": "Lebanon", "operator": "Safaricom", "company_wiki_url": "https://en.wikipedia.org/wiki/Safaricom"},
{"id": 93, "country": "Lebanon", "operator": "Airtel", "company_wiki_url": "https://en.wikipedia.org/wiki/Airtel_Africa"},
{"id": 94, "country": "Lebanon", "operator": "Telkom Kenya", "company_wiki_url": "https://en.wikipedia.org/wiki/Telkom_Kenya"},
{"id": 95, "country": "Lesotho", "operator": "Zain", "company_wiki_url": "https://en.wikipedia.org/wiki/Zain_Group"},
{"id": 96, "country": "Lesotho", "operator": "Ooredoo", "company_wiki_url": "https://en.wikipedia.org/wiki/Ooredoo"},
{"id": 97, "country": "Liberia", "operator": "touch", "company_wiki_url": "https://en.wikipedia.org/wiki/Mtc_touch"},
{"id": 98, "country": "Liberia", "operator": "Alfa", "company_wiki_url": "https://en.wikipedia.org/wiki/Alfa_(Lebanon)"},
{"id": 99, "country": "Libya", "operator": "Vodacom", "company_wiki_url": "https://en.wikipedia.org/wiki/Vodacom"},
{"id": 100, "country": "Libya", "operator": "Econet Telecom Lesotho", "company_wiki_url": "https://en.wikipedia.org/wiki/Econet_Telecom_Lesotho"},
{"id": 101, "country": "Madagascar", "operator": "Lonestar Cell MTN", "company_wiki_url": "https://en.wikipedia.org/wiki/Lonestar_Cell"},
{"id": 102, "country": "Madagascar", "operator": "Orange", "company_wiki_url": "https://en.wikipedia.org/wiki/Orange_S.A."},
{"id": 103, "country": "Madagascar", "operator": "LTC Mobile", "company_wiki_url": "https://en.wikipedia.org/wiki/Liberia_Telecommunications_Corporation"},
{"id": 104, "country": "Malawi", "operator": "Almadar Aljadid", "company_wiki_url": null},
{"id": 105, "country": "Malawi", "operator": "Libyana", "company_wiki_url": "https://en.wikipedia.org/wiki/Libyana"},
{"id": 106, "country": "Mali", "operator": "Airtel", "company_wiki_url": "https://en.wikipedia.org/wiki/Airtel_Africa"},
{"id": 107, "country": "Mali", "operator": "Orange", "company_wiki_url": "https://en.wikipedia.org/wiki/Orange_S.A."},
{"id": 108, "country": "Mauritania", "operator": "Airtel", "company_wiki_url": "https://en.wikipedia.org/wiki/Airtel_Africa"},
{"id": 109, "country": "Mauritania", "operator": "TNM", "company_wiki_url": "https://en.wikipedia.org/wiki/Telekom_Networks_Malawi"},
{"id": 110, "country": "Mauritania", "operator": "Access", "company_wiki_url": null},
{"id": 111, "country": "Mauritius", "operator": "Orange", "company_wiki_url": "https://en.wikipedia.org/wiki/Orange_S.A."},
{"id": 112, "country": "Mauritius", "operator": "Moov Africa Malitel", "company_wiki_url": "https://en.wikipedia.org/wiki/Malitel"},
{"id": 113, "country": "Mauritius", "operator": "Planor", "company_wiki_url": null},
{"id": 114, "country": "Morocco", "operator": "Moov Mauritel", "company_wiki_url": "https://en.wikipedia.org/wiki/Mauritel"},
{"id": 115, "country": "Morocco", "operator": "Chinguitel", "company_wiki_url": null},
{"id": 116, "country": "Morocco", "operator": "MATTEL", "company_wiki_url": null},
{"id": 117, "country": "Mozambique", "operator": "Mauritius Telecom", "company_wiki_url": "https://en.wikipedia.org/wiki/Mauritius_Telecom"},
{"id": 118, "country": "Mozambique", "operator": "Emtel", "company_wiki_url": "https://en.wikipedia.org/wiki/Emtel"},
{"id": 119, "country": "Mozambique", "operator": "CHiLi", "company_wiki_url": "https://en.wikipedia.org/wiki/MTML"},
{"id": 120, "country": "Namibia", "operator": "Maroc Telecom", "company_wiki_url": "https://en.wikipedia.org/wiki/Maroc_Telecom"},
{"id": 121, "country": "Namibia", "operator": "Orange Morocco", "company_wiki_url": "https://en.wikipedia.org/wiki/Orange_Morocco"},
{"id": 122, "country": "Namibia", "operator": "inwi", "company_wiki_url": "https://en.wikipedia.org/wiki/Wana_(Telecommunications)"},
{"id": 123, "country": "Niger", "operator": "Tmcel", "company_wiki_url": null},
{"id": 124, "country": "Niger", "operator": "Vodacom", "company_wiki_url": "https://en.wikipedia.org/wiki/Vodacom"},
{"id": 125, "country": "Niger", "operator": "Movitel", "company_wiki_url": "https://en.wikipedia.org/wiki/Movitel,_SA"},
{"id": 126, "country": "Nigeria", "operator": "MTC", "company_wiki_url": "https://en.wikipedia.org/wiki/MTC_Namibia"},
{"id": 127, "country": "Nigeria", "operator": "TN Mobile", "company_wiki_url": "https://en.wikipedia.org/wiki/TN_Mobile"},
{"id": 128, "country": "Oman", "operator": "Airtel", "company_wiki_url": "https://en.wikipedia.org/wiki/Airtel_Africa"},
{"id": 129, "country": "Palestine", "operator": "MTN", "company_wiki_url": "https://en.wikipedia.org/wiki/Mobile_Telephone_Networks"},
{"id": 130, "country": "Palestine", "operator": "Airtel", "company_wiki_url": "https://en.wikipedia.org/wiki/Airtel_Networks_Limited"},
{"id": 131, "country": "Palestine", "operator": "Glo Mobile", "company_wiki_url": "https://en.wikipedia.org/wiki/Globacom"},
{"id": 132, "country": "Qatar", "operator": "Omantel", "company_wiki_url": "https://en.wikipedia.org/wiki/Omantel"},
{"id": 133, "country": "Qatar", "operator": "Ooredoo", "company_wiki_url": "https://en.wikipedia.org/wiki/Ooredoo"},
{"id": 134, "country": "La Réunion", "operator": "Jawwal", "company_wiki_url": "https://en.wikipedia.org/wiki/Jawwal"},
{"id": 135, "country": "La Réunion", "operator": "Ooredoo", "company_wiki_url": "https://en.wikipedia.org/wiki/Ooredoo"},
{"id": 136, "country": "Rwanda", "operator": "Ooredoo", "company_wiki_url": "https://en.wikipedia.org/wiki/Ooredoo"},
{"id": 137, "country": "Rwanda", "operator": "Vodafone", "company_wiki_url": "https://en.wikipedia.org/wiki/Vodafone_Qatar"},
{"id": 138, "country": "São Tomé and Príncipe", "operator": "SFR", "company_wiki_url": "https://en.wikipedia.org/wiki/SFR"},
{"id": 139, "country": "São Tomé and Príncipe", "operator": "Orange", "company_wiki_url": "https://en.wikipedia.org/wiki/Orange_S.A."},
{"id": 140, "country": "São Tomé and Príncipe", "operator": "FREE", "company_wiki_url": "https://en.wikipedia.orghttps://fr.wikipedia.org/wiki/FREE"},
{"id": 141, "country": "Saudi Arabia", "operator": "MTN Rwanda", "company_wiki_url": "https://en.wikipedia.org/wiki/MTN_Rwanda"},
{"id": 142, "country": "Saudi Arabia", "operator": "Airtel", "company_wiki_url": "https://en.wikipedia.org/wiki/Airtel_Africa"},
{"id": 143, "country": "Saudi Arabia", "operator": "Rwandatel", "company_wiki_url": "https://en.wikipedia.org/wiki/Rwandatel"},
{"id": 144, "country": "Seychelles", "operator": "stc", "company_wiki_url": "https://en.wikipedia.org/wiki/Saudi_Telecom_Company"},
{"id": 145, "country": "Seychelles", "operator": "Mobily", "company_wiki_url": "https://en.wikipedia.org/wiki/Mobily"},
{"id": 146, "country": "Seychelles", "operator": "Zain", "company_wiki_url": "https://en.wikipedia.org/wiki/Zain_Saudi_Arabia"},
{"id": 147, "country": "Seychelles", "operator": "Virgin mobile KSA", "company_wiki_url": "https://en.wikipedia.org/wiki/Virgin_Mobile_Saudi_Arabia"},
{"id": 148, "country": "Sierra Leone", "operator": "Orange", "company_wiki_url": "https://en.wikipedia.org/wiki/Orange_S.A."},
{"id": 149, "country": "Sierra Leone", "operator": "Free", "company_wiki_url": "https://en.wikipedia.org/wiki/Free_(ISP)"},
{"id": 150, "country": "Sierra Leone", "operator": "Expresso", "company_wiki_url": "https://en.wikipedia.org/wiki/Expresso_Telecom"},
{"id": 151, "country": "Sierra Leone", "operator": "Hayo Telecom", "company_wiki_url": null},
{"id": 152, "country": "Somalia", "operator": "Airtel", "company_wiki_url": "https://en.wikipedia.org/wiki/Airtel_Africa"},
{"id": 153, "country": "Somalia", "operator": "Cable & Wireless", "company_wiki_url": "https://en.wikipedia.org/wiki/Cable_%26_Wireless_Worldwide"},
{"id": 154, "country": "Anguilla", "operator": "Digicel", "company_wiki_url": "https://en.wikipedia.org/wiki/Digicel"},
{"id": 155, "country": "South Africa", "operator": "Africell", "company_wiki_url": "https://en.wikipedia.org/wiki/Africell"},
{"id": 156, "country": "South Africa", "operator": "Orange", "company_wiki_url": "https://en.wikipedia.org/wiki/Orange_S.A."},
{"id": 157, "country": "South Africa", "operator": "Sierratel", "company_wiki_url": null},
{"id": 158, "country": "South Africa", "operator": "Qcell", "company_wiki_url": null},
{"id": 159, "country": "South Africa", "operator": "Comium", "company_wiki_url": null},
{"id": 160, "country": "South Africa", "operator": "GreenN", "company_wiki_url": null},
{"id": 161, "country": "South Sudan", "operator": "Hormuud", "company_wiki_url": "https://en.wikipedia.org/wiki/Hormuud_Telecom"},
{"id": 162, "country": "Anguilla", "operator": "FLOW", "company_wiki_url": "https://en.wikipedia.org/wiki/Flow_(brand)"},
{"id": 163, "country": "Antigua and Barbuda", "operator": "Digicel", "company_wiki_url": "https://en.wikipedia.org/wiki/Digicel"},
{"id": 164, "country": "Antigua and Barbuda", "operator": "FLOW", "company_wiki_url": "https://en.wikipedia.org/wiki/Flow_(brand)"},
{"id": 165, "country": "Argentina", "operator": "Claro", "company_wiki_url": "https://en.wikipedia.org/wiki/Claro_(mobile_phone_network)"},
{"id": 166, "country": "Argentina", "operator": "Movistar", "company_wiki_url": "https://en.wikipedia.org/wiki/Movistar"},
{"id": 167, "country": "Argentina", "operator": "Personal", "company_wiki_url": "https://en.wikipedia.org/wiki/Telecom_Personal"},
{"id": 168, "country": "Aruba", "operator": "Digicel", "company_wiki_url": "https://en.wikipedia.org/wiki/Digicel"},
{"id": 169, "country": "Aruba", "operator": "SetarNV", "company_wiki_url": "https://en.wikipedia.org/wiki/SetarNV"},
{"id": 170, "country": "South Sudan", "operator": "Telcom Somalia", "company_wiki_url": "https://en.wikipedia.org/wiki/Telcom_(Somalia)"},
{"id": 171, "country": "South Sudan", "operator": "Telesom Mobile", "company_wiki_url": "https://en.wikipedia.org/wiki/Telesom"},
{"id": 172, "country": "South Sudan", "operator": "Nationlink", "company_wiki_url": "https://en.wikipedia.org/wiki/NationLink_Telecom"},
{"id": 173, "country": "South Sudan", "operator": "Somtel", "company_wiki_url": "https://en.wikipedia.org/wiki/Somtel"},
{"id": 174, "country": "South Sudan", "operator": "Golis Telecom Somalia", "company_wiki_url": "https://en.wikipedia.org/wiki/Golis_Telecom_Somalia"},
{"id": 175, "country": "South Sudan", "operator": "Somafone", "company_wiki_url": "https://en.wikipedia.org/wiki/Somafone"},
{"id": 176, "country": "South Sudan", "operator": "Netco", "company_wiki_url": "https://en.wikipedia.org/wiki/Netco_(Somalia)"},
{"id": 177, "country": "South Sudan", "operator": "SomNet", "company_wiki_url": null},
{"id": 178, "country": "Sudan", "operator": "Vodacom", "company_wiki_url": "https://en.wikipedia.org/wiki/Vodacom"},
{"id": 179, "country": "Sudan", "operator": "MTN", "company_wiki_url": "https://en.wikipedia.org/wiki/MTN_Group"},
{"id": 180, "country": "Bahamas", "operator": "BTC", "company_wiki_url": "https://en.wikipedia.org/wiki/BTC_(Bahamas)"},
{"id": 181, "country": "Bahamas", "operator": "Aliv", "company_wiki_url": "https://en.wikipedia.org/wiki/Aliv"},
{"id": 182, "country": "Barbados", "operator": "FLOW", "company_wiki_url": "https://en.wikipedia.org/wiki/Flow_(brand)"},
{"id": 183, "country": "Barbados", "operator": "Digicel", "company_wiki_url": "https://en.wikipedia.org/wiki/Digicel"},
{"id": 184, "country": "Belize", "operator": "Smart", "company_wiki_url": "https://en.wikipedia.org/wiki/Speednet"},
{"id": 185, "country": "Bermuda", "operator": "One", "company_wiki_url": "https://en.wikipedia.org/wiki/Cell_One"},
{"id": 186, "country": "Bermuda", "operator": "Digicel", "company_wiki_url": "https://en.wikipedia.org/wiki/Digicel"},
{"id": 187, "country": "Sudan", "operator": "Cell C", "company_wiki_url": "https://en.wikipedia.org/wiki/Cell_C"},
{"id": 188, "country": "Sudan", "operator": "Telkom", "company_wiki_url": "https://en.wikipedia.org/wiki/Telkom_SA"},
{"id": 189, "country": "Sudan", "operator": "Rain", "company_wiki_url": "https://en.wikipedia.org/wiki/Rain_(telecommunications)"},
{"id": 190, "country": "Eswatini", "operator": "MTN", "company_wiki_url": "https://en.wikipedia.org/wiki/MTN_South_Sudan"},
{"id": 191, "country": "Eswatini", "operator": "Zain", "company_wiki_url": "https://en.wikipedia.org/wiki/Zain_South_Sudan"},
{"id": 192, "country": "Eswatini", "operator": "Sudani", "company_wiki_url": "https://en.wikipedia.org/wiki/Sudani"},
{"id": 193, "country": "Bolivia", "operator": "Entel", "company_wiki_url": "https://en.wikipedia.org/wiki/Entel_Bolivia"},
{"id": 194, "country": "Albania", "operator": "Vodafone", "company_wiki_url": "https://en.wikipedia.org/wiki/Vodafone_Albania"},
{"id": 195, "country": "Afghanistan", "operator": "MTN", "company_wiki_url": "https://en.wikipedia.org/wiki/MTN_Group"},
{"id": 196, "country": "Eswatini", "operator": "Vivacell", "company_wiki_url": null},
{"id": 197, "country": "Eswatini", "operator": "Gemtel", "company_wiki_url": null},
{"id": 198, "country": "Syrian Arab Republic", "operator": "Zain", "company_wiki_url": "https://en.wikipedia.org/wiki/Zain_Group"},
{"id": 199, "country": "Syrian Arab Republic", "operator": "MTN", "company_wiki_url": "https://en.wikipedia.org/wiki/MTN_Group"},
{"id": 200, "country": "Syrian Arab Republic", "operator": "Sudani", "company_wiki_url": "https://en.wikipedia.org/wiki/Sudani"},
{"id": 201, "country": "Tanzania (United Republic of)", "operator": "MTN", "company_wiki_url": "https://en.wikipedia.org/wiki/MTN_Group"},
{"id": 202, "country": "Bolivia", "operator": "Tigo", "company_wiki_url": null},
{"id": 203, "country": "Bolivia", "operator": "Viva", "company_wiki_url": "https://en.wikipedia.org/wiki/Viva_(Bolivia)"},
{"id": 204, "country": "Bonaire", "operator": "Digicel", "company_wiki_url": "https://en.wikipedia.org/wiki/Digicel"},
{"id": 205, "country": "Bonaire", "operator": "FLOW", "company_wiki_url": "https://en.wikipedia.org/wiki/FLOW_(brand)"},
{"id": 206, "country": "Brazil", "operator": "Vivo", "company_wiki_url": "https://en.wikipedia.org/wiki/Vivo_(telecommunications)"},
{"id": 207, "country": "Brazil", "operator": "Claro", "company_wiki_url": "https://en.wikipedia.org/wiki/Claro_Brasil"},
{"id": 208, "country": "Brazil", "operator": "TIM", "company_wiki_url": "https://en.wikipedia.org/wiki/TIM_Brasil"},
{"id": 209, "country": "Albania", "operator": "One Telecommunications", "company_wiki_url": "https://en.wikipedia.org/wiki/One_Telecommunications"},
{"id": 210, "country": "Albania", "operator": "ALBtelecom Mobile", "company_wiki_url": "https://en.wikipedia.org/wiki/ALBtelecom_Mobile"},
{"id": 211, "country": "Andorra", "operator": "Andorra Telecom", "company_wiki_url": "https://en.wikipedia.org/wiki/Andorra_Telecom"},
{"id": 212, "country": "Armenia", "operator": "VivaCell-MTS", "company_wiki_url": "https://en.wikipedia.org/wiki/MTS_(network_provider)"},
{"id": 213, "country": "Armenia", "operator": "Team Telecom Armenia", "company_wiki_url": "https://en.wikipedia.org/wiki/Telecom_Armenia"},
{"id": 214, "country": "Armenia", "operator": "Ucom", "company_wiki_url": "https://en.wikipedia.org/wiki/Ucom"},
{"id": 215, "country": "Austria", "operator": "A1", "company_wiki_url": "https://en.wikipedia.org/wiki/A1_Telekom_Austria"},
{"id": 216, "country": "Afghanistan", "operator": "Roshan", "company_wiki_url": "https://en.wikipedia.org/wiki/Roshan_(telco)"},
{"id": 217, "country": "Afghanistan", "operator": "Etisalat", "company_wiki_url": "https://en.wikipedia.org/wiki/Etisalat"},
{"id": 218, "country": "Afghanistan", "operator": "Afghan Wireless", "company_wiki_url": "https://en.wikipedia.org/wiki/AWCC"},
{"id": 219, "country": "Bangladesh", "operator": "Grameenphone", "company_wiki_url": "https://en.wikipedia.org/wiki/Grameenphone"},
{"id": 220, "country": "Bangladesh", "operator": "Robi", "company_wiki_url": "https://en.wikipedia.org/wiki/Robi_(company)"},
{"id": 221, "country": "Togo", "operator": "MTN", "company_wiki_url": "https://en.wikipedia.org/wiki/MTN_Group"},
{"id": 222, "country": "Togo", "operator": "Syriatel", "company_wiki_url": "https://en.wikipedia.org/wiki/Syriatel"},
{"id": 223, "country": "Tunisia", "operator": "Vodacom", "company_wiki_url": "https://en.wikipedia.org/wiki/Vodacom"},
{"id": 224, "country": "Tunisia", "operator": "Airtel", "company_wiki_url": "https://en.wikipedia.org/wiki/Airtel_Tanzania"},
{"id": 225, "country": "Tunisia", "operator": "Tigo", "company_wiki_url": "https://en.wikipedia.org/wiki/MIC_Tanzania_Limited"},
{"id": 226, "country": "Tunisia", "operator": "Halotel", "company_wiki_url": "https://en.wikipedia.org/wiki/Halotel"},
{"id": 227, "country": "Tunisia", "operator": "Zantel", "company_wiki_url": "https://en.wikipedia.org/wiki/Etisalat#Zantel_–_Tanzania"},
{"id": 228, "country": "Turkey", "operator": "Togocel", "company_wiki_url": null},
{"id": 229, "country": "Brazil", "operator": "Algar Telecom", "company_wiki_url": "https://en.wikipedia.org/wiki/Algar_Telecom"},
{"id": 230, "country": "British Virgin Islands", "operator": "FLOW", "company_wiki_url": "https://en.wikipedia.org/wiki/Flow_(brand)"},
{"id": 231, "country": "British Virgin Islands", "operator": "Digicel", "company_wiki_url": "https://en.wikipedia.org/wiki/Digicel"},
{"id": 232, "country": "Canada", "operator": "Rogers", "company_wiki_url": "https://en.wikipedia.org/wiki/Rogers_Wireless"},
{"id": 233, "country": "Canada", "operator": "Bell", "company_wiki_url": "https://en.wikipedia.org/wiki/Bell_Mobility"},
{"id": 234, "country": "Canada", "operator": "Telus", "company_wiki_url": "https://en.wikipedia.org/wiki/Telus_Mobility"},
{"id": 235, "country": "Canada", "operator": "Freedom Mobile", "company_wiki_url": "https://en.wikipedia.org/wiki/Freedom_Mobile"},
{"id": 236, "country": "Austria", "operator": "Magenta Telekom", "company_wiki_url": "https://en.wikipedia.org/wiki/Magenta_Telekom"},
{"id": 237, "country": "Austria", "operator": "Drei", "company_wiki_url": "https://en.wikipedia.org/wiki/Drei_Oesterreich"},
{"id": 238, "country": "Austria", "operator": "spusu", "company_wiki_url": "https://en.wikipedia.orghttps://de.wikipedia.org/wiki/spusu"},
{"id": 239, "country": "Azerbaijan", "operator": "Azercell", "company_wiki_url": "https://en.wikipedia.org/wiki/Azercell"},
{"id": 240, "country": "Azerbaijan", "operator": "Nar", "company_wiki_url": "https://en.wikipedia.org/wiki/Nar_Mobile"},
{"id": 241, "country": "Azerbaijan", "operator": "Nakhtel", "company_wiki_url": "https://en.wikipedia.org/wiki/Nakhtel"},
{"id": 242, "country": "Belarus", "operator": "MTS", "company_wiki_url": "https://en.wikipedia.org/wiki/MTS_(network_provider)"},
{"id": 243, "country": "Bangladesh", "operator": "Banglalink", "company_wiki_url": "https://en.wikipedia.org/wiki/Banglalink"},
{"id": 244, "country": "Bangladesh", "operator": "Teletalk", "company_wiki_url": "https://en.wikipedia.org/wiki/Teletalk"},
{"id": 245, "country": "Bhutan", "operator": "B-Mobile", "company_wiki_url": "https://en.wikipedia.org/wiki/B-Mobile_(Bhutan)"},
{"id": 246, "country": "Bougainville", "operator": "PNG dataco", "company_wiki_url": null},
{"id": 247, "country": "Brunei Darussalam", "operator": "Progresif Cellular Sdn Bhd", "company_wiki_url": "https://en.wikipedia.org/wiki/Progresif_Cellular_Sdn_Bhd"},
{"id": 248, "country": "Uganda", "operator": "Ooredoo", "company_wiki_url": "https://en.wikipedia.org/wiki/Ooredoo"},
{"id": 249, "country": "Uganda", "operator": "Tunisie Telecom", "company_wiki_url": "https://en.wikipedia.org/wiki/Tunisie_Telecom"},
{"id": 250, "country": "Uganda", "operator": "Orange", "company_wiki_url": "https://en.wikipedia.org/wiki/Orange_S.A."},
{"id": 251, "country": "United Arab Emirates", "operator": "Turkcell", "company_wiki_url": "https://en.wikipedia.org/wiki/Turkcell"},
{"id": 252, "country": "United Arab Emirates", "operator": "Vodafone", "company_wiki_url": "https://en.wikipedia.org/wiki/Vodafone_Turkey"},
{"id": 253, "country": "United Arab Emirates", "operator": "Türk Telekom", "company_wiki_url": "https://en.wikipedia.org/wiki/T%C3%BCrk_Telekom"},
{"id": 254, "country": "Yemen", "operator": "MTN", "company_wiki_url": "https://en.wikipedia.org/wiki/MTN_Group"},
{"id": 255, "country": "Canada", "operator": "Vidéotron", "company_wiki_url": "https://en.wikipedia.org/wiki/Vid%C3%A9otron_Mobile"},
{"id": 256, "country": "Canada", "operator": "SaskTel", "company_wiki_url": "https://en.wikipedia.org/wiki/SaskTel_Mobility"},
{"id": 257, "country": "Cayman Islands", "operator": "FLOW Cayman", "company_wiki_url": "https://en.wikipedia.org/wiki/Flow_(brand)"},
{"id": 258, "country": "Cayman Islands", "operator": "Digicel", "company_wiki_url": "https://en.wikipedia.org/wiki/Digicel"},
{"id": 259, "country": "Chile", "operator": "Entel", "company_wiki_url": "https://en.wikipedia.org/wiki/Entel_(Chile)"},
{"id": 260, "country": "Chile", "operator": "Movistar", "company_wiki_url": "https://en.wikipedia.org/wiki/Movistar"},
{"id": 261, "country": "Chile", "operator": "Claro", "company_wiki_url": "https://en.wikipedia.org/wiki/Claro_(mobile_phone_network)"},
{"id": 262, "country": "Belarus", "operator": "A1", "company_wiki_url": "https://en.wikipedia.org/wiki/A1_Belarus"},
{"id": 263, "country": "Belgium", "operator": "Proximus", "company_wiki_url": "https://en.wikipedia.org/wiki/Proximus"},
{"id": 264, "country": "Belgium", "operator": "Orange", "company_wiki_url": "https://en.wikipedia.org/wiki/Orange_Belgium"},
{"id": 265, "country": "Belgium", "operator": "Base", "company_wiki_url": "https://en.wikipedia.org/wiki/Base_(mobile_telephony_provider)"},
{"id": 266, "country": "Bosnia and Herzegovina", "operator": "BH Telecom", "company_wiki_url": "https://en.wikipedia.org/wiki/BH_Telecom"},
{"id": 267, "country": "Bosnia and Herzegovina", "operator": "m:tel", "company_wiki_url": "https://en.wikipedia.org/wiki/Mtel_Bosnia_and_Herzegovina"},
{"id": 268, "country": "Bosnia and Herzegovina", "operator": "HT Eronet", "company_wiki_url": "https://en.wikipedia.org/wiki/HT_Eronet"},
{"id": 269, "country": "Bulgaria", "operator": "A1", "company_wiki_url": "https://en.wikipedia.org/wiki/A1_Bulgaria"},
{"id": 270, "country": "Cambodia", "operator": "Metfone", "company_wiki_url": null},
{"id": 271, "country": "Cambodia", "operator": "Smart", "company_wiki_url": "https://en.wikipedia.org/wiki/Smart_Axiata"},
{"id": 272, "country": "Cambodia", "operator": "Cellcard", "company_wiki_url": null},
{"id": 273, "country": "China (mainland)", "operator": "China Mobile", "company_wiki_url": "https://en.wikipedia.org/wiki/China_Mobile"},
{"id": 274, "country": "China (mainland)", "operator": "China Telecom", "company_wiki_url": "https://en.wikipedia.org/wiki/China_Telecom"},
{"id": 275, "country": "China (mainland)", "operator": "China Unicom", "company_wiki_url": "https://en.wikipedia.org/wiki/China_Unicom"},
{"id": 276, "country": "Fiji", "operator": "Vodafone", "company_wiki_url": "https://en.wikipedia.org/wiki/Vodafone_fiji"},
{"id": 277, "country": "Yemen", "operator": "Airtel", "company_wiki_url": "https://en.wikipedia.org/wiki/Airtel_(India)"},
{"id": 278, "country": "Yemen", "operator": "Africell", "company_wiki_url": "https://en.wikipedia.org/wiki/Africell"},
{"id": 279, "country": "Yemen", "operator": "Warid", "company_wiki_url": "https://en.wikipedia.org/wiki/Warid_Telecom"},
{"id": 280, "country": "Yemen", "operator": "Essar", "company_wiki_url": "https://en.wikipedia.org/wiki/Essar"},
{"id": 281, "country": "Zambia", "operator": "Etisalat", "company_wiki_url": "https://en.wikipedia.org/wiki/Etisalat"},
{"id": 282, "country": "Zambia", "operator": "du", "company_wiki_url": "https://en.wikipedia.org/wiki/Du_(telco)"},
{"id": 283, "country": "Zimbabwe", "operator": "Yemen Mobile", "company_wiki_url": "https://en.wikipedia.org/wiki/Yemen_Mobile"},
{"id": 284, "country": "Zimbabwe", "operator": "Sabafon", "company_wiki_url": "https://en.wikipedia.org/wiki/Sabafon"},
{"id": 285, "country": "Chile", "operator": "VTR Móvil", "company_wiki_url": "https://en.wikipedia.org/wiki/VTR_(telecom_company)"},
{"id": 286, "country": "Chile", "operator": "Virgin Mobile", "company_wiki_url": "https://en.wikipedia.org/wiki/Virgin_Mobile_Chile"},
{"id": 287, "country": "Colombia", "operator": "Claro", "company_wiki_url": "https://en.wikipedia.org/wiki/Claro_Colombia"},
{"id": 288, "country": "Colombia", "operator": "Movistar", "company_wiki_url": "https://en.wikipedia.org/wiki/Movistar"},
{"id": 289, "country": "Colombia", "operator": "Tigo", "company_wiki_url": "https://en.wikipedia.org/wiki/Colombia_M%C3%B3vil"},
{"id": 290, "country": "Colombia", "operator": "Virgin Mobile", "company_wiki_url": "https://en.wikipedia.org/wiki/Virgin_Mobile#Virgin_Mobile_Colombia"},
{"id": 291, "country": "Colombia", "operator": "Móvil Éxito", "company_wiki_url": "https://en.wikipedia.org/wiki/Grupo_%C3%89xito"},
{"id": 292, "country": "Colombia", "operator": "ETB", "company_wiki_url": "https://en.wikipedia.org/wiki/ETB_(company)"},
{"id": 293, "country": "Costa Rica", "operator": "Claro", "company_wiki_url": "https://en.wikipedia.org/wiki/Claro_Americas"},
{"id": 294, "country": "Bulgaria", "operator": "Yettel", "company_wiki_url": "https://en.wikipedia.org/wiki/Yettel_Bulgaria"},
{"id": 295, "country": "Bulgaria", "operator": "Vivacom", "company_wiki_url": "https://en.wikipedia.org/wiki/Vivacom"},
{"id": 296, "country": "Fiji", "operator": "Digicel", "company_wiki_url": "https://en.wikipedia.org/wiki/Digicel"},
{"id": 297, "country": "French Polynesia", "operator": "Vodafone", "company_wiki_url": "https://en.wikipedia.org/wiki/Vodafone"},
{"id": 298, "country": "Curaçao", "operator": "FLOW", "company_wiki_url": "https://en.wikipedia.org/wiki/FLOW_(brand)"},
{"id": 299, "country": "Dominica", "operator": "Digicel", "company_wiki_url": "https://en.wikipedia.org/wiki/Digicel"},
{"id": 300, "country": "Dominica", "operator": "FLOW", "company_wiki_url": "https://en.wikipedia.org/wiki/Flow_(brand)"},
{"id": 301, "country": "Croatia", "operator": "Hrvatski Telekom", "company_wiki_url": "https://en.wikipedia.org/wiki/Hrvatski_Telekom"},
{"id": 302, "country": "Croatia", "operator": "A1", "company_wiki_url": "https://en.wikipedia.org/wiki/A1_Hrvatska"},
{"id": 303, "country": "Croatia", "operator": "Telemach", "company_wiki_url": "https://en.wikipedia.orghttps://hr.wikipedia.org/wiki/Telemach_Hrvatska"},
{"id": 304, "country": "Cyprus", "operator": "Epic", "company_wiki_url": "https://en.wikipedia.org/wiki/Monaco_Telecom#Europe"},
{"id": 305, "country": "Guam", "operator": "Docomo Pacific", "company_wiki_url": "https://en.wikipedia.org/wiki/Docomo_Pacific"},
{"id": 306, "country": "Guam", "operator": "GTA", "company_wiki_url": "https://en.wikipedia.org/wiki/GTA_Teleguam"},
{"id": 307, "country": "Hong Kong", "operator": "CMHK", "company_wiki_url": "https://en.wikipedia.org/wiki/CMHK"},
{"id": 308, "country": "Hong Kong", "operator": "HKT", "company_wiki_url": "https://en.wikipedia.org/wiki/Hong_Kong_Telecom"},
{"id": 309, "country": "Hong Kong", "operator": "3 Hong Kong", "company_wiki_url": "https://en.wikipedia.org/wiki/3_Hong_Kong"},
{"id": 310, "country": "Hong Kong", "operator": "SmarTone", "company_wiki_url": "https://en.wikipedia.org/wiki/SmarTone"},
{"id": 311, "country": "Dominican Republic", "operator": "Claro", "company_wiki_url": "https://en.wikipedia.org/wiki/Claro_Rep%C3%BAblica_Dominicana"},
{"id": 312, "country": "Dominican Republic", "operator": "altice", "company_wiki_url": "https://en.wikipedia.org/wiki/Altice_Dominicana_S.A."},
{"id": 313, "country": "Dominican Republic", "operator": "Viva", "company_wiki_url": "https://en.wikipedia.org/wiki/Trilogy_Dominicana_(Viva)"},
{"id": 314, "country": "Ecuador", "operator": "Claro", "company_wiki_url": "https://en.wikipedia.org/wiki/Claro_Americas"},
{"id": 315, "country": "Ecuador", "operator": "Movistar", "company_wiki_url": "https://en.wikipedia.org/wiki/Movistar"},
{"id": 316, "country": "Ecuador", "operator": "Cnt", "company_wiki_url": "https://en.wikipedia.org/wiki/CNT_EP"},
{"id": 317, "country": "Cyprus", "operator": "Cytamobile", "company_wiki_url": "https://en.wikipedia.org/wiki/CYTA"},
{"id": 318, "country": "Cyprus", "operator": "PrimeTel", "company_wiki_url": "https://en.wikipedia.org/wiki/PrimeTel"},
{"id": 319, "country": "Cyprus", "operator": "Kuzey Kıbrıs Turkcell", "company_wiki_url": "https://en.wikipedia.org/wiki/Kuzey_K%C4%B1br%C4%B1s_Turkcell"},
{"id": 320, "country": "Cyprus", "operator": "Telsim Vodafone", "company_wiki_url": "https://en.wikipedia.org/wiki/KKTC_Telsim"},
{"id": 321, "country": "Czech Republic", "operator": "T-Mobile", "company_wiki_url": "https://en.wikipedia.org/wiki/T-Mobile_Czech_Republic"},
{"id": 322, "country": "Czech Republic", "operator": "O", "company_wiki_url": "https://en.wikipedia.org/wiki/O2_Czech_Republic"},
{"id": 323, "country": "Czech Republic", "operator": "Vodafone", "company_wiki_url": "https://en.wikipedia.org/wiki/Vodafone_Czech_Republic"},
{"id": 324, "country": "Denmark", "operator": "TDC", "company_wiki_url": "https://en.wikipedia.org/wiki/TDC_Holding_A/S"},
{"id": 325, "country": "Denmark", "operator": "Telenor", "company_wiki_url": "https://en.wikipedia.org/wiki/Telenor_Denmark"},
{"id": 326, "country": "Hong Kong", "operator": "HKBN", "company_wiki_url": "https://en.wikipedia.org/wiki/Hong_Kong_Broadband_Network_Limited"},
{"id": 327, "country": "Hong Kong", "operator": "Birdie", "company_wiki_url": null},
{"id": 328, "country": "Hong Kong", "operator": "SmarTone", "company_wiki_url": "https://en.wikipedia.org/wiki/SmarTone"},
{"id": 329, "country": "Hong Kong", "operator": "Mobile Duck", "company_wiki_url": null},
{"id": 330, "country": "Hong Kong", "operator": "CMHK", "company_wiki_url": "https://en.wikipedia.org/wiki/CMHK"},
{"id": 331, "country": "Hong Kong", "operator": "MO+", "company_wiki_url": null},
{"id": 332, "country": "Hong Kong", "operator": "3 Hong Kong", "company_wiki_url": "https://en.wikipedia.org/wiki/3_Hong_Kong"},
{"id": 333, "country": "Hong Kong", "operator": "ValueGB", "company_wiki_url": null},
{"id": 334, "country": "Hong Kong", "operator": "SmarTone", "company_wiki_url": "https://en.wikipedia.org/wiki/SmarTone"},
{"id": 335, "country": "Hong Kong", "operator": "MB", "company_wiki_url": null},
{"id": 336, "country": "Hong Kong", "operator": "CMHK", "company_wiki_url": "https://en.wikipedia.org/wiki/CMHK"},
{"id": 337, "country": "Hong Kong", "operator": "IMC", "company_wiki_url": null},
{"id": 338, "country": "Hong Kong", "operator": "HKT", "company_wiki_url": "https://en.wikipedia.org/wiki/Hong_Kong_Telecom"},
{"id": 339, "country": "Hong Kong", "operator": "China Unicom", "company_wiki_url": null},
{"id": 340, "country": "Hong Kong", "operator": "3 Hong Kong", "company_wiki_url": "https://en.wikipedia.org/wiki/3_Hong_Kong"},
{"id": 341, "country": "Hong Kong", "operator": "CTExcel", "company_wiki_url": null},
{"id": 342, "country": "El Salvador", "operator": "Tigo", "company_wiki_url": "https://en.wikipedia.org/wiki/Tigo_El_Salvador"},
{"id": 343, "country": "El Salvador", "operator": "Claro", "company_wiki_url": "https://en.wikipedia.org/wiki/Claro_El_Salvador"},
{"id": 344, "country": "El Salvador", "operator": "Movistar", "company_wiki_url": "https://en.wikipedia.org/wiki/Movistar"},
{"id": 345, "country": "El Salvador", "operator": "Digicel", "company_wiki_url": "https://en.wikipedia.org/wiki/Digicel"},
{"id": 346, "country": "Falkland Islands", "operator": "Sure", "company_wiki_url": "https://en.wikipedia.org/wiki/Sure_(company)"},
{"id": 347, "country": "Greenland", "operator": "tusass", "company_wiki_url": "https://en.wikipedia.org/wiki/TELE_Greenland"},
{"id": 348, "country": "Denmark", "operator": "Telia", "company_wiki_url": "https://en.wikipedia.org/wiki/Telia_Company#Denmark"},
{"id": 349, "country": "Denmark", "operator": "3", "company_wiki_url": "https://en.wikipedia.org/wiki/3_(telecommunications)#Denmark_and_Sweden"},
{"id": 350, "country": "Estonia", "operator": "Telia", "company_wiki_url": "https://en.wikipedia.org/wiki/Telia_Eesti"},
{"id": 351, "country": "Estonia", "operator": "Elisa", "company_wiki_url": "https://en.wikipedia.org/wiki/Elisa_(company)"},
{"id": 352, "country": "Estonia", "operator": "Tele2", "company_wiki_url": "https://en.wikipedia.org/wiki/Tele2#Estonia"},
{"id": 353, "country": "Faroe Islands", "operator": "Føroya Tele", "company_wiki_url": "https://en.wikipedia.org/wiki/F%C3%B8roya_Tele"},
{"id": 354, "country": "Faroe Islands", "operator": "Hey", "company_wiki_url": "https://en.wikipedia.org/wiki/Hey_(company)"},
{"id": 355, "country": "Finland", "operator": "Elisa", "company_wiki_url": "https://en.wikipedia.org/wiki/Elisa_(company)"},
{"id": 356, "country": "Hong Kong", "operator": "HKT", "company_wiki_url": "https://en.wikipedia.org/wiki/Hong_Kong_Telecom"},
{"id": 357, "country": "Indonesia", "operator": "Telkomsel", "company_wiki_url": "https://en.wikipedia.org/wiki/Telkomsel"},
{"id": 358, "country": "Indonesia", "operator": "Indosat Ooredoo Hutchison", "company_wiki_url": "https://en.wikipedia.org/wiki/Indosat"},
{"id": 359, "country": "Indonesia", "operator": "XL Axiata", "company_wiki_url": "https://en.wikipedia.org/wiki/XL_Axiata"},
{"id": 360, "country": "Indonesia", "operator": "Smartfren", "company_wiki_url": "https://en.wikipedia.org/wiki/Smartfren"},
{"id": 361, "country": "Japan", "operator": "NTT Docomo", "company_wiki_url": "https://en.wikipedia.org/wiki/NTT_Docomo"},
{"id": 362, "country": "Grenada", "operator": "FLOW", "company_wiki_url": "https://en.wikipedia.org/wiki/Flow_(brand)"},
{"id": 363, "country": "Grenada", "operator": "Digicel", "company_wiki_url": "https://en.wikipedia.org/wiki/Digicel"},
{"id": 364, "country": "Guadeloupe, Martinique and French Guiana (Guyane)", "operator": "Digicel", "company_wiki_url": "https://en.wikipedia.org/wiki/Digicel"},
{"id": 365, "country": "Guadeloupe, Martinique and French Guiana (Guyane)", "operator": "SFR Caraïbe", "company_wiki_url": null},
{"id": 366, "country": "Guatemala", "operator": "Tigo", "company_wiki_url": "https://en.wikipedia.org/wiki/Tigo_Guatemala"},
{"id": 367, "country": "Guatemala", "operator": "Claro", "company_wiki_url": "https://en.wikipedia.org/wiki/Claro_(mobile_phone_network)"},
{"id": 368, "country": "Guyana", "operator": "Digicel", "company_wiki_url": "https://en.wikipedia.org/wiki/Digicel"},
{"id": 369, "country": "Finland", "operator": "Telia", "company_wiki_url": "https://en.wikipedia.org/wiki/Telia_Company#Finland"},
{"id": 370, "country": "Finland", "operator": "DNA", "company_wiki_url": "https://en.wikipedia.org/wiki/DNA_Oyj"},
{"id": 371, "country": "Finland", "operator": "Ålcom", "company_wiki_url": "https://en.wikipedia.org/wiki/%C3%85lcom"},
{"id": 372, "country": "France", "operator": "Orange", "company_wiki_url": "https://en.wikipedia.org/wiki/Orange_S.A."},
{"id": 373, "country": "France", "operator": "SFR", "company_wiki_url": "https://en.wikipedia.org/wiki/SFR"},
{"id": 374, "country": "France", "operator": "Bouygues Telecom", "company_wiki_url": "https://en.wikipedia.org/wiki/Bouygues_Telecom"},
{"id": 375, "country": "France", "operator": "Free Mobile", "company_wiki_url": "https://en.wikipedia.org/wiki/Free_Mobile"},
{"id": 376, "country": "Georgia", "operator": "Magticom", "company_wiki_url": "https://en.wikipedia.org/wiki/MagtiCom"},
{"id": 377, "country": "Japan", "operator": "au", "company_wiki_url": "https://en.wikipedia.org/wiki/Au_(mobile_phone_operator)"},
{"id": 378, "country": "Japan", "operator": "SoftBank Corp.", "company_wiki_url": "https://en.wikipedia.org/wiki/SoftBank_Mobile"},
{"id": 379, "country": "Japan", "operator": "Ymobile", "company_wiki_url": "https://en.wikipedia.org/wiki/Ymobile"},
{"id": 380, "country": "Japan", "operator": "Rakuten Mobile", "company_wiki_url": "https://en.wikipedia.org/wiki/Rakuten_Mobile"},
{"id": 381, "country": "Japan", "operator": "Disney Mobile", "company_wiki_url": "https://en.wikipedia.org/wiki/Disney_Mobile"},
{"id": 382, "country": "Kazakhstan", "operator": "Beeline", "company_wiki_url": "https://en.wikipedia.org/wiki/VimpelCom"},
{"id": 383, "country": "Kazakhstan", "operator": "Kcell", "company_wiki_url": "https://en.wikipedia.org/wiki/Kcell"},
{"id": 384, "country": "Kazakhstan", "operator": "Tele2 Kazakhstan", "company_wiki_url": null},
{"id": 385, "country": "Kyrgyzstan", "operator": "Beeline", "company_wiki_url": "https://en.wikipedia.org/wiki/Beeline_(telecommunications)"},
{"id": 386, "country": "Haiti", "operator": "Digicel", "company_wiki_url": "https://en.wikipedia.org/wiki/Digicel"},
{"id": 387, "country": "Honduras", "operator": "Tigo", "company_wiki_url": "https://en.wikipedia.org/wiki/Tigo"},
{"id": 388, "country": "Honduras", "operator": "Claro", "company_wiki_url": "https://en.wikipedia.org/wiki/Claro_(mobile_phone_network)"},
{"id": 389, "country": "Honduras", "operator": "HONDUTEL", "company_wiki_url": "https://en.wikipedia.org/wiki/Hondutel"},
{"id": 390, "country": "Jamaica", "operator": "Digicel", "company_wiki_url": "https://en.wikipedia.org/wiki/Digicel"},
{"id": 391, "country": "Georgia", "operator": "Silknet", "company_wiki_url": "https://en.wikipedia.org/wiki/Silknet"},
{"id": 392, "country": "Georgia", "operator": "Beeline", "company_wiki_url": "https://en.wikipedia.org/wiki/Beeline_(brand)"},
{"id": 393, "country": "Germany", "operator": "Telekom", "company_wiki_url": "https://en.wikipedia.org/wiki/Telekom_Deutschland"},
{"id": 394, "country": "Germany", "operator": "O", "company_wiki_url": "https://en.wikipedia.org/wiki/Telef%C3%B3nica_Germany"},
{"id": 395, "country": "Germany", "operator": "Vodafone", "company_wiki_url": "https://en.wikipedia.org/wiki/Vodafone_Germany"},
{"id": 396, "country": "Gibraltar", "operator": "Gibtelecom", "company_wiki_url": "https://en.wikipedia.org/wiki/Gibtelecom"},
{"id": 397, "country": "Greece", "operator": "Cosmote", "company_wiki_url": "https://en.wikipedia.org/wiki/Cosmote"},
{"id": 398, "country": "Laos", "operator": "Unitel", "company_wiki_url": null},
{"id": 399, "country": "Laos", "operator": "LaoTelecom", "company_wiki_url": null},
{"id": 400, "country": "Laos", "operator": "TPLUS", "company_wiki_url": null},
{"id": 401, "country": "Laos", "operator": "ETL", "company_wiki_url": null},
{"id": 402, "country": "Macau", "operator": "CTM", "company_wiki_url": "https://en.wikipedia.org/wiki/CTM_(Macau)"},
{"id": 403, "country": "Macau", "operator": "China Telecom", "company_wiki_url": "https://en.wikipedia.org/wiki/China_Telecom"},
{"id": 404, "country": "Jamaica", "operator": "FLOW", "company_wiki_url": "https://en.wikipedia.org/wiki/FLOW_Jamaica"},
{"id": 405, "country": "Greece", "operator": "Vodafone", "company_wiki_url": "https://en.wikipedia.org/wiki/Vodafone_Greece"},
{"id": 406, "country": "Greece", "operator": "Nova", "company_wiki_url": "https://en.wikipedia.org/wiki/Nova_(Greece)"},
{"id": 407, "country": "Guernsey", "operator": "Sure", "company_wiki_url": "https://en.wikipedia.org/wiki/Sure_(company)"},
{"id": 408, "country": "Guernsey", "operator": "JT", "company_wiki_url": "https://en.wikipedia.org/wiki/JT_Group_Limited"},
{"id": 409, "country": "Guernsey", "operator": "Airtel-Vodafone", "company_wiki_url": "https://en.wikipedia.org/wiki/Airtel-Vodafone"},
{"id": 410, "country": "Macau", "operator": "3 Macau", "company_wiki_url": "https://en.wikipedia.org/wiki/Hutchison_3G"},
{"id": 411, "country": "Macau", "operator": "SmarTone", "company_wiki_url": "https://en.wikipedia.org/wiki/SmarTone"},
{"id": 412, "country": "Malaysia", "operator": "Digi", "company_wiki_url": "https://en.wikipedia.org/wiki/Digi_Telecommunications"},
{"id": 413, "country": "Malaysia", "operator": "Celcom", "company_wiki_url": "https://en.wikipedia.org/wiki/Celcom"},
{"id": 414, "country": "Malaysia", "operator": "Maxis", "company_wiki_url": "https://en.wikipedia.org/wiki/Maxis_Communications"},
{"id": 415, "country": "Malaysia", "operator": "U Mobile", "company_wiki_url": "https://en.wikipedia.org/wiki/U_Mobile"},
{"id": 416, "country": "Malaysia", "operator": "Yes 4G", "company_wiki_url": "https://en.wikipedia.org/wiki/Yes_4G"},
{"id": 417, "country": "Mexico", "operator": "Telcel", "company_wiki_url": "https://en.wikipedia.org/wiki/Telcel"},
{"id": 418, "country": "Mexico", "operator": "Movistar", "company_wiki_url": "https://en.wikipedia.org/wiki/Movistar"},
{"id": 419, "country": "Mexico", "operator": "AT&T Mexico", "company_wiki_url": "https://en.wikipedia.org/wiki/AT%26T_Mexico"},
{"id": 420, "country": "Mexico", "operator": "Unefón", "company_wiki_url": "https://en.wikipedia.org/wiki/Unef%C3%B3n"},
{"id": 421, "country": "Mexico", "operator": "Red Compartida", "company_wiki_url": "https://en.wikipedia.org/wiki/Red_Compartida"},
{"id": 422, "country": "Mexico", "operator": "Virgin Mobile", "company_wiki_url": "https://en.wikipedia.org/wiki/Virgin_Mobile"},
{"id": 423, "country": "Mexico", "operator": "Movistar", "company_wiki_url": "https://en.wikipedia.org/wiki/Movistar"},
{"id": 424, "country": "Mexico", "operator": "QBO Cel", "company_wiki_url": null},
{"id": 425, "country": "Mexico", "operator": "Movistar", "company_wiki_url": "https://en.wikipedia.org/wiki/Movistar"},
{"id": 426, "country": "Mexico", "operator": "weex", "company_wiki_url": null},
{"id": 427, "country": "Mexico", "operator": "Movistar", "company_wiki_url": "https://en.wikipedia.org/wiki/Movistar"},
{"id": 428, "country": "Hungary", "operator": "Telekom", "company_wiki_url": "https://en.wikipedia.org/wiki/Magyar_Telekom"},
{"id": 429, "country": "Hungary", "operator": "Yettel", "company_wiki_url": "https://en.wikipedia.org/wiki/Yettel_Hungary"},
{"id": 430, "country": "Hungary", "operator": "Vodafone", "company_wiki_url": "https://en.wikipedia.org/wiki/Vodafone_Hungary"},
{"id": 431, "country": "Hungary", "operator": "Digi", "company_wiki_url": "https://en.wikipedia.org/wiki/Digi_Communications"},
{"id": 432, "country": "Iceland", "operator": "Síminn", "company_wiki_url": "https://en.wikipedia.org/wiki/S%C3%ADminn"},
{"id": 433, "country": "Iceland", "operator": "Nova", "company_wiki_url": "https://en.wikipedia.org/wiki/Nova_(telecommunications)"},
{"id": 434, "country": "Iceland", "operator": "Vodafone", "company_wiki_url": "https://en.wikipedia.org/wiki/Vodafone_Iceland"},
{"id": 435, "country": "Ireland", "operator": "Three", "company_wiki_url": "https://en.wikipedia.org/wiki/Three_Ireland"},
{"id": 436, "country": "Malaysia", "operator": "Unifi Mobile", "company_wiki_url": "https://en.wikipedia.org/wiki/Unifi_Mobile"},
{"id": 437, "country": "Malaysia", "operator": "Digital Nasional Berhad", "company_wiki_url": "https://en.wikipedia.org/wiki/Digital_Nasional_Berhad"},
{"id": 438, "country": "Malaysia", "operator": "XOX", "company_wiki_url": "https://en.wikipedia.org/wiki/XOX"},
{"id": 439, "country": "Malaysia", "operator": "TuneTalk", "company_wiki_url": "https://en.wikipedia.org/wiki/TuneTalk"},
{"id": 440, "country": "Malaysia", "operator": "Merchantrade", "company_wiki_url": "https://en.wikipedia.org/wiki/Merchantrade_Asia"},
{"id": 441, "country": "Maldives", "operator": "Dhiraagu", "company_wiki_url": "https://en.wikipedia.org/wiki/Dhiraagu"},
{"id": 442, "country": "Maldives", "operator": "Ooredoo Maldives", "company_wiki_url": "https://en.wikipedia.org/wiki/Ooredoo_Maldives"},
{"id": 443, "country": "Micronesia, Federated States of", "operator": "FSM Telecom", "company_wiki_url": null},
{"id": 444, "country": "Mexico", "operator": "Cierto", "company_wiki_url": null},
{"id": 445, "country": "Mexico", "operator": "Movistar", "company_wiki_url": "https://en.wikipedia.org/wiki/Movistar"},
{"id": 446, "country": "Mexico", "operator": "Maz Tiempo", "company_wiki_url": null},
{"id": 447, "country": "Mexico", "operator": "Movistar", "company_wiki_url": "https://en.wikipedia.org/wiki/Movistar"},
{"id": 448, "country": "Mexico", "operator": "Telcel", "company_wiki_url": "https://en.wikipedia.org/wiki/Telcel"},
{"id": 449, "country": "Mexico", "operator": "Flash Mobile", "company_wiki_url": null},
{"id": 450, "country": "Mexico", "operator": "Movistar", "company_wiki_url": "https://en.wikipedia.org/wiki/Movistar"},
{"id": 451, "country": "Montserrat", "operator": "FLOW", "company_wiki_url": "https://en.wikipedia.org/wiki/FLOW_(Brand)"},
{"id": 452, "country": "Montserrat", "operator": "Digicel", "company_wiki_url": "https://en.wikipedia.org/wiki/Digicel"},
{"id": 453, "country": "Nicaragua", "operator": "Claro", "company_wiki_url": "https://en.wikipedia.org/wiki/Claro_Americas"},
{"id": 454, "country": "Nicaragua", "operator": "Tigo", "company_wiki_url": "https://en.wikipedia.org/wiki/Tigo"},
{"id": 455, "country": "Panama", "operator": "+móvil", "company_wiki_url": "https://en.wikipedia.org/wiki/Cable_%26_Wireless_Communications#Panama"},
{"id": 456, "country": "Ireland", "operator": "Vodafone", "company_wiki_url": "https://en.wikipedia.org/wiki/Vodafone_Ireland"},
{"id": 457, "country": "Ireland", "operator": "eir", "company_wiki_url": "https://en.wikipedia.org/wiki/Eir_(telecommunications)"},
{"id": 458, "country": "Isle of Man", "operator": "Manx Telecom", "company_wiki_url": "https://en.wikipedia.org/wiki/Manx_Telecom"},
{"id": 459, "country": "Isle of Man", "operator": "Sure", "company_wiki_url": "https://en.wikipedia.org/wiki/Sure_(company)"},
{"id": 460, "country": "Italy", "operator": "Wind Tre", "company_wiki_url": "https://en.wikipedia.org/wiki/Wind_Tre"},
{"id": 461, "country": "Italy", "operator": "TIM", "company_wiki_url": "https://en.wikipedia.org/wiki/Telecom_Italia_Mobile"},
{"id": 462, "country": "Italy", "operator": "Vodafone", "company_wiki_url": "https://en.wikipedia.org/wiki/Vodafone_Italy"},
{"id": 463, "country": "Italy", "operator": "Iliad", "company_wiki_url": "https://en.wikipedia.org/wiki/Iliad_Italia"},
{"id": 464, "country": "Italy", "operator": "Fastweb", "company_wiki_url": "https://en.wikipedia.org/wiki/Fastweb_(telecommunications_company)"},
{"id": 465, "country": "Mongolia", "operator": "Mobicom", "company_wiki_url": "https://en.wikipedia.org/wiki/Mobicom_Corporation"},
{"id": 466, "country": "Mongolia", "operator": "Unitel", "company_wiki_url": "https://en.wikipedia.org/wiki/Unitel_(Mongolia)"},
{"id": 467, "country": "Mongolia", "operator": "Skytel", "company_wiki_url": "https://en.wikipedia.org/wiki/Skytel_(Mongolia)"},
{"id": 468, "country": "Mongolia", "operator": "G-Mobile", "company_wiki_url": "https://en.wikipedia.org/wiki/G-Mobile"},
{"id": 469, "country": "Myanmar", "operator": "MPT", "company_wiki_url": "https://en.wikipedia.org/wiki/Myanmar_Posts_and_Telecommunications"},
{"id": 470, "country": "Myanmar", "operator": "Telenor", "company_wiki_url": "https://en.wikipedia.org/wiki/Telenor_Myanmar"},
{"id": 471, "country": "Myanmar", "operator": "Ooredoo", "company_wiki_url": "https://en.wikipedia.org/wiki/Ooredoo_Myanmar"},
{"id": 472, "country": "Panama", "operator": "Tigo", "company_wiki_url": "https://en.wikipedia.org/wiki/Tigo"},
{"id": 473, "country": "Panama", "operator": "Claro", "company_wiki_url": "https://en.wikipedia.org/wiki/Claro_(mobile_phone_network)"},
{"id": 474, "country": "Panama", "operator": "Digicel", "company_wiki_url": "https://en.wikipedia.org/wiki/Digicel"},
{"id": 475, "country": "Paraguay", "operator": "Tigo", "company_wiki_url": null},
{"id": 476, "country": "Paraguay", "operator": "Personal", "company_wiki_url": null},
{"id": 477, "country": "Paraguay", "operator": "Claro", "company_wiki_url": null},
{"id": 478, "country": "Paraguay", "operator": "VOX", "company_wiki_url": null},
{"id": 479, "country": "Peru", "operator": "Movistar", "company_wiki_url": "https://en.wikipedia.org/wiki/Movistar"},
{"id": 480, "country": "Peru", "operator": "Claro", "company_wiki_url": "https://en.wikipedia.org/wiki/Claro_(mobile_phone_network)"},
{"id": 481, "country": "Peru", "operator": "Entel", "company_wiki_url": null},
{"id": 482, "country": "Peru", "operator": "Bitel", "company_wiki_url": null},
{"id": 483, "country": "Jersey", "operator": "JT", "company_wiki_url": "https://en.wikipedia.org/wiki/JT_Group_Limited"},
{"id": 484, "country": "Jersey", "operator": "Sure", "company_wiki_url": "https://en.wikipedia.org/wiki/Sure_(company)"},
{"id": 485, "country": "Jersey", "operator": "Airtel-Vodafone", "company_wiki_url": "https://en.wikipedia.org/wiki/Airtel-Vodafone"},
{"id": 486, "country": "Kosovo", "operator": "Vala", "company_wiki_url": "https://en.wikipedia.org/wiki/Kosovo_Telecom"},
{"id": 487, "country": "Kosovo", "operator": "Ipko", "company_wiki_url": "https://en.wikipedia.org/wiki/IPKO"},
{"id": 488, "country": "Kosovo", "operator": "mts", "company_wiki_url": "https://en.wikipedia.org/wiki/Mts_(Telekom_Srbija)"},
{"id": 489, "country": "Latvia", "operator": "LMT", "company_wiki_url": "https://en.wikipedia.org/wiki/Latvian_Mobile_Telephone"},
{"id": 490, "country": "Myanmar", "operator": "Mytel", "company_wiki_url": "https://en.wikipedia.org/wiki/Mytel"},
{"id": 491, "country": "Nauru", "operator": "Digicel", "company_wiki_url": "https://en.wikipedia.org/wiki/Digicel"},
{"id": 492, "country": "Nepal", "operator": "Ncell", "company_wiki_url": "https://en.wikipedia.org/wiki/Ncell"},
{"id": 493, "country": "Nepal", "operator": "Nepal Telecom", "company_wiki_url": "https://en.wikipedia.org/wiki/Nepal_Telecom"},
{"id": 494, "country": "Nepal", "operator": "SmartCell", "company_wiki_url": "https://en.wikipedia.org/wiki/SmartCell"},
{"id": 495, "country": "New Caledonia", "operator": "Mobilis", "company_wiki_url": null},
{"id": 496, "country": "Peru", "operator": "Cuy Móvil", "company_wiki_url": null},
{"id": 497, "country": "Peru", "operator": "Claro", "company_wiki_url": "https://en.wikipedia.org/wiki/Claro_(mobile_phone_network)"},
{"id": 498, "country": "Puerto Rico and United States Virgin Islands", "operator": "Liberty", "company_wiki_url": "https://en.wikipedia.org/wiki/Liberty_Puerto_Rico"},
{"id": 499, "country": "Puerto Rico and United States Virgin Islands", "operator": "Claro", "company_wiki_url": "https://en.wikipedia.org/wiki/Claro_Puerto_Rico"},
{"id": 500, "country": "Puerto Rico and United States Virgin Islands", "operator": "T-Mobile", "company_wiki_url": "https://en.wikipedia.org/wiki/T-Mobile_US"},
{"id": 501, "country": "Puerto Rico and United States Virgin Islands", "operator": "TracFone Wireless", "company_wiki_url": "https://en.wikipedia.org/wiki/TracFone_Wireless"},
{"id": 502, "country": "Saint Kitts and Nevis", "operator": "FLOW", "company_wiki_url": "https://en.wikipedia.org/wiki/Flow_(brand)"},
{"id": 503, "country": "Saint Kitts and Nevis", "operator": "Digicel", "company_wiki_url": "https://en.wikipedia.org/wiki/Digicel"},
{"id": 504, "country": "Saint Lucia", "operator": "FLOW", "company_wiki_url": "https://en.wikipedia.org/wiki/Flow_(brand)"},
{"id": 505, "country": "Latvia", "operator": "Tele2", "company_wiki_url": "https://en.wikipedia.org/wiki/Tele2"},
{"id": 506, "country": "Latvia", "operator": "Bite", "company_wiki_url": null},
{"id": 507, "country": "Latvia", "operator": "Triatel", "company_wiki_url": null},
{"id": 508, "country": "Liechtenstein", "operator": "FL1", "company_wiki_url": null},
{"id": 509, "country": "Liechtenstein", "operator": "7acht", "company_wiki_url": null},
{"id": 510, "country": "Liechtenstein", "operator": "Swisscom FL", "company_wiki_url": "https://en.wikipedia.org/wiki/Swisscom"},
{"id": 511, "country": "Lithuania", "operator": "Tele2", "company_wiki_url": "https://en.wikipedia.org/wiki/Tele2#Lithuania"},
{"id": 512, "country": "Lithuania", "operator": "Telia", "company_wiki_url": "https://en.wikipedia.org/wiki/Telia_Company#Lithuania"},
{"id": 513, "country": "Lithuania", "operator": "Bitė", "company_wiki_url": "https://en.wikipedia.org/wiki/Bit%C4%97_Group"},
{"id": 514, "country": "New Zealand", "operator": "Vodafone", "company_wiki_url": "https://en.wikipedia.org/wiki/Vodafone_New_Zealand"},
{"id": 515, "country": "New Zealand", "operator": "Spark", "company_wiki_url": "https://en.wikipedia.org/wiki/Spark_New_Zealand"},
{"id": 516, "country": "New Zealand", "operator": "2degrees", "company_wiki_url": "https://en.wikipedia.org/wiki/2degrees"},
{"id": 517, "country": "New Zealand", "operator": "Compass Mobile", "company_wiki_url": null},
{"id": 518, "country": "New Zealand", "operator": "Orcon Mobile", "company_wiki_url": null},
{"id": 519, "country": "New Zealand", "operator": "Slingshot Mobile", "company_wiki_url": null},
{"id": 520, "country": "Niue", "operator": "Telecom Niue", "company_wiki_url": null},
{"id": 521, "country": "Saint Lucia", "operator": "Digicel", "company_wiki_url": "https://en.wikipedia.org/wiki/Digicel"},
{"id": 522, "country": "Saint Vincent and the Grenadines", "operator": "FLOW", "company_wiki_url": "https://en.wikipedia.org/wiki/Flow_(brand)"},
{"id": 523, "country": "Saint Vincent and the Grenadines", "operator": "Digicel", "company_wiki_url": "https://en.wikipedia.org/wiki/Digicel"},
{"id": 524, "country": "Suriname", "operator": "Telesur", "company_wiki_url": "https://en.wikipedia.org/wiki/Telesur_(Suriname)"},
{"id": 525, "country": "Luxembourg", "operator": "Orange", "company_wiki_url": "https://en.wikipedia.org/wiki/Orange_S.A."},
{"id": 526, "country": "Luxembourg", "operator": "Tango", "company_wiki_url": "https://en.wikipedia.org/wiki/Tango_(telecom)"},
{"id": 527, "country": "Luxembourg", "operator": "POST", "company_wiki_url": "https://en.wikipedia.org/wiki/Post_Luxembourg"},
{"id": 528, "country": "Luxembourg", "operator": "Luxembourg Online", "company_wiki_url": "https://en.wikipedia.orghttps://fr.wikipedia.org/wiki/Luxembourg_Online"},
{"id": 529, "country": "Malta", "operator": "Epic", "company_wiki_url": "https://en.wikipedia.org/wiki/Epic_(Malta)"},
{"id": 530, "country": "North Korea", "operator": "Koryolink", "company_wiki_url": "https://en.wikipedia.org/wiki/Koryolink"},
{"id": 531, "country": "Northern Mariana Islands", "operator": "Docomo Pacific", "company_wiki_url": "https://en.wikipedia.org/wiki/NTT_DoCoMo"},
{"id": 532, "country": "Northern Mariana Islands", "operator": "IT&E", "company_wiki_url": null},
{"id": 533, "country": "Pakistan", "operator": "Jazz", "company_wiki_url": "https://en.wikipedia.org/wiki/Jazz_Pakistan"},
{"id": 534, "country": "Suriname", "operator": "Digicel", "company_wiki_url": "https://en.wikipedia.org/wiki/Digicel"},
{"id": 535, "country": "Turks and Caicos Islands", "operator": "Digicel", "company_wiki_url": "https://en.wikipedia.org/wiki/Digicel"},
{"id": 536, "country": "Turks and Caicos Islands", "operator": "FLOW", "company_wiki_url": "https://en.wikipedia.org/wiki/Flow_(brand)"},
{"id": 537, "country": "United States", "operator": "Verizon", "company_wiki_url": "https://en.wikipedia.org/wiki/Verizon_(mobile_network)"},
{"id": 538, "country": "United States", "operator": "T-Mobile US", "company_wiki_url": "https://en.wikipedia.org/wiki/T-Mobile_US"},
{"id": 539, "country": "Malta", "operator": "GO", "company_wiki_url": "https://en.wikipedia.org/wiki/GO_(Malta)"},
{"id": 540, "country": "Malta", "operator": "Melita", "company_wiki_url": "https://en.wikipedia.org/wiki/Melita_(telecommunications_company)"},
{"id": 541, "country": "Moldova", "operator": "Orange", "company_wiki_url": "https://en.wikipedia.org/wiki/Orange_Moldova"},
{"id": 542, "country": "Moldova", "operator": "Moldcell", "company_wiki_url": "https://en.wikipedia.org/wiki/Moldcell"},
{"id": 543, "country": "Moldova", "operator": "Moldtelecom", "company_wiki_url": "https://en.wikipedia.org/wiki/Moldtelecom"},
{"id": 544, "country": "Moldova", "operator": "Interdnestrcom", "company_wiki_url": "https://en.wikipedia.org/wiki/Interdnestrcom"},
{"id": 545, "country": "Monaco", "operator": "Monaco Telecom", "company_wiki_url": "https://en.wikipedia.org/wiki/Monaco_Telecom"},
{"id": 546, "country": "Pakistan", "operator": "Telenor Pakistan", "company_wiki_url": "https://en.wikipedia.org/wiki/Telenor_Pakistan"},
{"id": 547, "country": "Pakistan", "operator": "Zong", "company_wiki_url": "https://en.wikipedia.org/wiki/Zong_Pakistan"},
{"id": 548, "country": "Pakistan", "operator": "Ufone", "company_wiki_url": "https://en.wikipedia.org/wiki/Ufone"},
{"id": 549, "country": "Pakistan", "operator": "SCOM", "company_wiki_url": "https://en.wikipedia.org/wiki/Special_Communications_Organization"},
{"id": 550, "country": "Palau", "operator": "PNCC", "company_wiki_url": null},
{"id": 551, "country": "Papua New Guinea", "operator": "Digicel", "company_wiki_url": "https://en.wikipedia.org/wiki/Digicel"},
{"id": 552, "country": "Papua New Guinea", "operator": "Telikom PNG", "company_wiki_url": null},
{"id": 553, "country": "Samoa", "operator": "Digicel", "company_wiki_url": "https://en.wikipedia.org/wiki/Digicel"},
{"id": 554, "country": "United States", "operator": "AT&T Mobility", "company_wiki_url": "https://en.wikipedia.org/wiki/AT%26T_Mobility"},
{"id": 555, "country": "United States", "operator": "Dish Wireless", "company_wiki_url": "https://en.wikipedia.org/wiki/Dish_Wireless"},
{"id": 556, "country": "United States", "operator": "U.S. Cellular", "company_wiki_url": "https://en.wikipedia.org/wiki/U.S._Cellular"},
{"id": 557, "country": "Uruguay", "operator": "Antel", "company_wiki_url": "https://en.wikipedia.org/wiki/Antel"},
{"id": 558, "country": "Uruguay", "operator": "Movistar", "company_wiki_url": "https://en.wikipedia.org/wiki/Movistar"},
{"id": 559, "country": "Uruguay", "operator": "Claro", "company_wiki_url": "https://en.wikipedia.org/wiki/Claro_Americas"},
{"id": 560, "country": "Venezuela", "operator": "Movilnet", "company_wiki_url": "https://en.wikipedia.org/wiki/Movilnet"},
{"id": 561, "country": "Venezuela", "operator": "Movistar", "company_wiki_url": "https://en.wikipedia.org/wiki/Movistar"},
{"id": 562, "country": "Venezuela", "operator": "Digitel GSM", "company_wiki_url": "https://en.wikipedia.org/wiki/Digitel_GSM"},
{"id": 563, "country": "Montenegro", "operator": "m:tel", "company_wiki_url": "https://en.wikipedia.org/wiki/Mtel_Montenegro"},
{"id": 564, "country": "Montenegro", "operator": "Telekom", "company_wiki_url": "https://en.wikipedia.org/wiki/Crnogorski_Telekom#Telekom"},
{"id": 565, "country": "Montenegro", "operator": "One", "company_wiki_url": "https://en.wikipedia.org/wiki/One_Montenegro"},
{"id": 566, "country": "Netherlands", "operator": "T-Mobile", "company_wiki_url": "https://en.wikipedia.org/wiki/T-Mobile_Netherlands"},
{"id": 567, "country": "Netherlands", "operator": "KPN", "company_wiki_url": "https://en.wikipedia.org/wiki/KPN"},
{"id": 568, "country": "Netherlands", "operator": "Vodafone", "company_wiki_url": "https://en.wikipedia.org/wiki/Vodafone_Netherlands"},
{"id": 569, "country": "North Macedonia", "operator": "Telekom", "company_wiki_url": "https://en.wikipedia.org/wiki/Makedonski_Telekom"},
{"id": 570, "country": "Singapore", "operator": "Singtel Mobile", "company_wiki_url": "https://en.wikipedia.org/wiki/Singtel"},
{"id": 571, "country": "Singapore", "operator": "StarHub", "company_wiki_url": "https://en.wikipedia.org/wiki/StarHub"},
{"id": 572, "country": "Singapore", "operator": "M1", "company_wiki_url": "https://en.wikipedia.org/wiki/M1_Limited"},
{"id": 573, "country": "Singapore", "operator": "SIMBA", "company_wiki_url": "https://en.wikipedia.org/wiki/Simba_Telecom"},
{"id": 574, "country": "Singapore", "operator": "GRID Communications", "company_wiki_url": null},
{"id": 575, "country": "Singapore", "operator": "Circles.Life", "company_wiki_url": "https://en.wikipedia.org/wiki/Circles.Life"},
{"id": 576, "country": "Singapore", "operator": "M1", "company_wiki_url": "https://en.wikipedia.org/wiki/MobileOne"},
{"id": 577, "country": "Singapore", "operator": "Zero1", "company_wiki_url": null},
{"id": 578, "country": "Singapore", "operator": "Singtel", "company_wiki_url": "https://en.wikipedia.org/wiki/Singtel"},
{"id": 579, "country": "Singapore", "operator": "MyRepublic", "company_wiki_url": "https://en.wikipedia.org/wiki/MyRepublic"},
{"id": 580, "country": "North Macedonia", "operator": "A1", "company_wiki_url": "https://en.wikipedia.org/wiki/A1_Macedonia"},
{"id": 581, "country": "Norway", "operator": "Telenor", "company_wiki_url": "https://en.wikipedia.org/wiki/Telenor"},
{"id": 582, "country": "Norway", "operator": "Telia", "company_wiki_url": "https://en.wikipedia.org/wiki/Telia_Norge"},
{"id": 583, "country": "Norway", "operator": "Ice", "company_wiki_url": "https://en.wikipedia.orghttps://no.wikipedia.org/wiki/Ice_Communication_Norge"},
{"id": 584, "country": "Poland", "operator": "Orange", "company_wiki_url": "https://en.wikipedia.org/wiki/Orange_Polska"},
{"id": 585, "country": "Poland", "operator": "Play", "company_wiki_url": "https://en.wikipedia.org/wiki/Play_(telecommunications)"},
{"id": 586, "country": "Poland", "operator": "Plus", "company_wiki_url": "https://en.wikipedia.org/wiki/Plus_(telecommunications_Poland)"},
{"id": 587, "country": "Poland", "operator": "T-Mobile", "company_wiki_url": "https://en.wikipedia.org/wiki/T-Mobile_Polska"},
{"id": 588, "country": "Singapore", "operator": "StarHub", "company_wiki_url": "https://en.wikipedia.org/wiki/StarHub"},
{"id": 589, "country": "Singapore", "operator": "M1", "company_wiki_url": "https://en.wikipedia.org/wiki/MobileOne"},
{"id": 590, "country": "Singapore", "operator": "redONE", "company_wiki_url": null},
{"id": 591, "country": "Singapore", "operator": "StarHub", "company_wiki_url": "https://en.wikipedia.org/wiki/StarHub"},
{"id": 592, "country": "Singapore", "operator": "VIVIFI", "company_wiki_url": null},
{"id": 593, "country": "Singapore", "operator": "Singtel", "company_wiki_url": "https://en.wikipedia.org/wiki/Singtel"},
{"id": 594, "country": "Singapore", "operator": "Geenet Mobile", "company_wiki_url": null},
{"id": 595, "country": "Singapore", "operator": "M1", "company_wiki_url": "https://en.wikipedia.org/wiki/MobileOne"},
{"id": 596, "country": "Singapore", "operator": "China Mobile", "company_wiki_url": "https://en.wikipedia.org/wiki/China_Mobile"},
{"id": 597, "country": "Singapore", "operator": "Singtel", "company_wiki_url": "https://en.wikipedia.org/wiki/Singtel"},
{"id": 598, "country": "Singapore", "operator": "ZYM", "company_wiki_url": null},
{"id": 599, "country": "Singapore", "operator": "Singtel", "company_wiki_url": "https://en.wikipedia.org/wiki/Singtel"},
{"id": 600, "country": "Singapore", "operator": "M1", "company_wiki_url": "https://en.wikipedia.org/wiki/MobileOne"},
{"id": 601, "country": "Singapore", "operator": "Gorilla Mobile", "company_wiki_url": null},
{"id": 602, "country": "Singapore", "operator": "M1", "company_wiki_url": "https://en.wikipedia.org/wiki/MobileOne"},
{"id": 603, "country": "South Korea", "operator": "SK Telecom", "company_wiki_url": "https://en.wikipedia.org/wiki/SK_Telecom"},
{"id": 604, "country": "Portugal", "operator": "MEO", "company_wiki_url": "https://en.wikipedia.org/wiki/Meo_(telecommunication_company)"},
{"id": 605, "country": "Portugal", "operator": "NOS", "company_wiki_url": "https://en.wikipedia.org/wiki/NOS_(Portuguese_company)"},
{"id": 606, "country": "Portugal", "operator": "Vodafone", "company_wiki_url": "https://en.wikipedia.org/wiki/Vodafone_Portugal"},
{"id": 607, "country": "Romania", "operator": "Orange", "company_wiki_url": "https://en.wikipedia.org/wiki/Orange_Romania"},
{"id": 608, "country": "Romania", "operator": "Vodafone", "company_wiki_url": "https://en.wikipedia.org/wiki/Vodafone_Romania"},
{"id": 609, "country": "Romania", "operator": "Digi", "company_wiki_url": "https://en.wikipedia.org/wiki/Digi_Communications"},
{"id": 610, "country": "Romania", "operator": "Telekom", "company_wiki_url": "https://en.wikipedia.org/wiki/Telekom_Romania_Mobile"},
{"id": 611, "country": "Russia", "operator": "MTS", "company_wiki_url": "https://en.wikipedia.org/wiki/MTS_(network_provider)"},
{"id": 612, "country": "South Korea", "operator": "KT", "company_wiki_url": "https://en.wikipedia.org/wiki/KT_Corporation"},
{"id": 613, "country": "South Korea", "operator": "LG U", "company_wiki_url": "https://en.wikipedia.org/wiki/LG_Uplus"},
{"id": 614, "country": "Sri Lanka", "operator": "Dialog", "company_wiki_url": "https://en.wikipedia.org/wiki/Dialog_Axiata"},
{"id": 615, "country": "Sri Lanka", "operator": "SLTMobitel", "company_wiki_url": "https://en.wikipedia.org/wiki/SLTMobitel"},
{"id": 616, "country": "Sri Lanka", "operator": "Hutch", "company_wiki_url": "https://en.wikipedia.org/wiki/Hutch_(Sri_Lanka)"},
{"id": 617, "country": "Sri Lanka", "operator": "Airtel", "company_wiki_url": "https://en.wikipedia.org/wiki/Airtel_Sri_Lanka"},
{"id": 618, "country": "Taiwan", "operator": "Chunghwa Telecom", "company_wiki_url": "https://en.wikipedia.org/wiki/Chunghwa_Telecom"},
{"id": 619, "country": "Taiwan", "operator": "Taiwan Mobile", "company_wiki_url": "https://en.wikipedia.org/wiki/Taiwan_Mobile"},
{"id": 620, "country": "Russia", "operator": "MegaFon", "company_wiki_url": "https://en.wikipedia.org/wiki/MegaFon"},
{"id": 621, "country": "Russia", "operator": "Beeline", "company_wiki_url": "https://en.wikipedia.org/wiki/Beeline_(brand)"},
{"id": 622, "country": "Russia", "operator": "Tele2 Russia", "company_wiki_url": "https://en.wikipedia.org/wiki/Tele2_Russia"},
{"id": 623, "country": "San Marino", "operator": "Telefonia Mobile Sammarinese", "company_wiki_url": null},
{"id": 624, "country": "Serbia", "operator": "mts", "company_wiki_url": "https://en.wikipedia.org/wiki/Telekom_Srbija#Mobile_telephony"},
{"id": 625, "country": "Serbia", "operator": "Yettel", "company_wiki_url": "https://en.wikipedia.org/wiki/Yettel_Serbia"},
{"id": 626, "country": "Serbia", "operator": "A1", "company_wiki_url": "https://en.wikipedia.org/wiki/A1_Srbija"},
{"id": 627, "country": "Slovakia", "operator": "Orange", "company_wiki_url": "https://en.wikipedia.org/wiki/Orange_Slovensko"},
{"id": 628, "country": "Taiwan", "operator": "Far EasTone", "company_wiki_url": "https://en.wikipedia.org/wiki/Far_EasTone"},
{"id": 629, "country": "Taiwan", "operator": "T STAR", "company_wiki_url": "https://en.wikipedia.org/wiki/Taiwan_Star_Telecom"},
{"id": 630, "country": "Taiwan", "operator": "Circles.Life", "company_wiki_url": "https://en.wikipedia.org/wiki/Circles.Life"},
{"id": 631, "country": "Taiwan", "operator": "Chunghwa", "company_wiki_url": "https://en.wikipedia.org/wiki/Chunghwa_Telecom"},
{"id": 632, "country": "Taiwan", "operator": "Ibon Mobile", "company_wiki_url": null},
{"id": 633, "country": "Slovakia", "operator": "O", "company_wiki_url": "https://en.wikipedia.org/wiki/O2_Slovakia"},
{"id": 634, "country": "Slovakia", "operator": "Telekom", "company_wiki_url": "https://en.wikipedia.org/wiki/Slovak_Telekom"},
{"id": 635, "country": "Slovakia", "operator": "4ka", "company_wiki_url": "https://en.wikipedia.orghttps://sk.wikipedia.org/wiki/4ka"},
{"id": 636, "country": "Slovenia", "operator": "Telekom Slovenije", "company_wiki_url": "https://en.wikipedia.org/wiki/Telekom_Slovenije"},
{"id": 637, "country": "Slovenia", "operator": "A1", "company_wiki_url": "https://en.wikipedia.org/wiki/A1_Slovenija"},
{"id": 638, "country": "Slovenia", "operator": "Telemach", "company_wiki_url": "https://en.wikipedia.org/wiki/Telemach_(Slovenia)"},
{"id": 639, "country": "Taiwan", "operator": "FarEasTone", "company_wiki_url": "https://en.wikipedia.org/wiki/FarEasTone"},
{"id": 640, "country": "Tajikistan", "operator": "Tcell", "company_wiki_url": "https://en.wikipedia.org/wiki/Tcell"},
{"id": 641, "country": "Tajikistan", "operator": "Babilon-Mobile", "company_wiki_url": null},
{"id": 642, "country": "Tajikistan", "operator": "ZET Mobile", "company_wiki_url": null},
{"id": 643, "country": "Tajikistan", "operator": "MegaFon", "company_wiki_url": "https://en.wikipedia.org/wiki/MegaFon#Tajikistan"},
{"id": 644, "country": "Thailand", "operator": "AIS", "company_wiki_url": "https://en.wikipedia.org/wiki/Advanced_Info_Service"},
{"id": 645, "country": "Slovenia", "operator": "T-2", "company_wiki_url": "https://en.wikipedia.org/wiki/T-2_(ISP)"},
{"id": 646, "country": "Spain", "operator": "Movistar", "company_wiki_url": "https://en.wikipedia.org/wiki/Movistar"},
{"id": 647, "country": "Spain", "operator": "Orange", "company_wiki_url": "https://en.wikipedia.org/wiki/Orange_Espa%C3%B1a"},
{"id": 648, "country": "Spain", "operator": "Vodafone", "company_wiki_url": "https://en.wikipedia.org/wiki/Vodafone_Espa%C3%B1a"},
{"id": 649, "country": "Spain", "operator": "Yoigo", "company_wiki_url": "https://en.wikipedia.org/wiki/Yoigo"},
{"id": 650, "country": "Sweden", "operator": "Telia", "company_wiki_url": "https://en.wikipedia.org/wiki/Telia_Company"},
{"id": 651, "country": "Thailand", "operator": "TrueMove H", "company_wiki_url": "https://en.wikipedia.org/wiki/True_Corporation"},
{"id": 652, "country": "Thailand", "operator": "Dtac", "company_wiki_url": "https://en.wikipedia.org/wiki/Dtac"},
{"id": 653, "country": "Thailand", "operator": "my by NT", "company_wiki_url": "https://en.wikipedia.org/wiki/CAT_Telecom"},
{"id": 654, "country": "Thailand", "operator": "NT Mobile", "company_wiki_url": "https://en.wikipedia.org/wiki/TOT_(Thailand)"},
{"id": 655, "country": "Timor-Leste", "operator": "Telemor", "company_wiki_url": null},
{"id": 656, "country": "Timor-Leste", "operator": "Timor Telecom", "company_wiki_url": "https://en.wikipedia.org/wiki/Timor_Telecom"},
{"id": 657, "country": "Timor-Leste", "operator": "Telkomcel", "company_wiki_url": "https://en.wikipedia.org/wiki/Telkomcel"},
{"id": 658, "country": "Tonga", "operator": "Digicel", "company_wiki_url": "https://en.wikipedia.org/wiki/Digicel"},
{"id": 659, "country": "Tonga", "operator": "TCC", "company_wiki_url": null},
{"id": 660, "country": "Turkmenistan", "operator": "AȘTU", "company_wiki_url": "https://en.wikipedia.org/wiki/Ashgabat_City_Telephone_Network"},
{"id": 661, "country": "Sweden", "operator": "Tele2", "company_wiki_url": "https://en.wikipedia.org/wiki/Tele2#Sweden"},
{"id": 662, "country": "Sweden", "operator": "Telenor", "company_wiki_url": "https://en.wikipedia.org/wiki/Telenor_Sverige"},
{"id": 663, "country": "Sweden", "operator": "Tre", "company_wiki_url": "https://en.wikipedia.org/wiki/3_(telecommunications)#Denmark_and_Sweden"},
{"id": 664, "country": "Switzerland", "operator": "Swisscom", "company_wiki_url": "https://en.wikipedia.org/wiki/Swisscom"},
{"id": 665, "country": "Switzerland", "operator": "Sunrise", "company_wiki_url": "https://en.wikipedia.org/wiki/Sunrise_Communications_AG"},
{"id": 666, "country": "Switzerland", "operator": "Salt", "company_wiki_url": "https://en.wikipedia.org/wiki/Salt_Mobile_SA"},
{"id": 667, "country": "Turkey", "operator": "Turkcell", "company_wiki_url": "https://en.wikipedia.org/wiki/Turkcell"},
{"id": 668, "country": "Tuvalu", "operator": "TTC", "company_wiki_url": "https://en.wikipedia.org/wiki/Tuvalu_Telecommunications_Corporation"},
{"id": 669, "country": "Uzbekistan", "operator": "UCell", "company_wiki_url": "https://en.wikipedia.org/wiki/Telia_(company)#Uzbekistan"},
{"id": 670, "country": "Uzbekistan", "operator": "Beeline", "company_wiki_url": "https://en.wikipedia.org/wiki/VimpelCom"},
{"id": 671, "country": "Uzbekistan", "operator": "Mobi.UZ", "company_wiki_url": "https://en.wikipedia.org/wiki/Universal_Mobile_Systems"},
{"id": 672, "country": "Uzbekistan", "operator": "Uzmobile", "company_wiki_url": null},
{"id": 673, "country": "Uzbekistan", "operator": "Perfectum", "company_wiki_url": null},
{"id": 674, "country": "Vanuatu", "operator": "Vodafone Vanuatu", "company_wiki_url": null},
{"id": 675, "country": "Turkey", "operator": "Vodafone", "company_wiki_url": "https://en.wikipedia.org/wiki/Vodafone_Turkey"},
{"id": 676, "country": "Turkey", "operator": "Türk Telekom", "company_wiki_url": "https://en.wikipedia.org/wiki/T%C3%BCrk_Telekom"},
{"id": 677, "country": "Ukraine", "operator": "Kyivstar", "company_wiki_url": "https://en.wikipedia.org/wiki/Kyivstar"},
{"id": 678, "country": "Ukraine", "operator": "Vodafone", "company_wiki_url": "https://en.wikipedia.org/wiki/Vodafone_Ukraine"},
{"id": 679, "country": "Ukraine", "operator": "lifecell", "company_wiki_url": "https://en.wikipedia.org/wiki/Lifecell"},
{"id": 680, "country": "Ukraine", "operator": "Intertelecom", "company_wiki_url": "https://en.wikipedia.org/wiki/Intertelecom"},
{"id": 681, "country": "Ukraine", "operator": "TriMob", "company_wiki_url": "https://en.wikipedia.org/wiki/TriMob"},
{"id": 682, "country": "Ukraine", "operator": "PEOPLEnet", "company_wiki_url": "https://en.wikipedia.org/wiki/PEOPLEnet"},
{"id": 683, "country": "United Kingdom", "operator": "O2", "company_wiki_url": "https://en.wikipedia.org/wiki/O2_(UK)"},
{"id": 684, "country": "Vanuatu", "operator": "Digicel", "company_wiki_url": "https://en.wikipedia.org/wiki/Digicel"},
{"id": 685, "country": "Vanuatu", "operator": "WanTok", "company_wiki_url": null},
{"id": 686, "country": "Vietnam", "operator": "Viettel Mobile", "company_wiki_url": "https://en.wikipedia.org/wiki/Viettel_Mobile"},
{"id": 687, "country": "Vietnam", "operator": "MobiFone", "company_wiki_url": "https://en.wikipedia.org/wiki/MobiFone"},
{"id": 688, "country": "Vietnam", "operator": "Vinaphone", "company_wiki_url": "https://en.wikipedia.org/wiki/Vinaphone"},
{"id": 689, "country": "Vietnam", "operator": "Vietnamobile", "company_wiki_url": "https://en.wikipedia.org/wiki/Vietnamobile"},
{"id": 690, "country": "Vietnam", "operator": "Gmobile", "company_wiki_url": "https://en.wikipedia.org/wiki/Gmobile"},
{"id": 691, "country": "United Kingdom", "operator": "EE", "company_wiki_url": "https://en.wikipedia.org/wiki/EE_Limited"},
{"id": 692, "country": "United Kingdom", "operator": "Vodafone", "company_wiki_url": "https://en.wikipedia.org/wiki/Vodafone_UK"},
{"id": 693, "country": "United Kingdom", "operator": "Three", "company_wiki_url": "https://en.wikipedia.org/wiki/Three_UK"}
]